Workbook

Sheet Get Started
A1: WELCOME TO YOUR WEDDING PLANNER
A3: Partner 1 Name | B3: Partner 2 Name | C3: Wedding Date | D3: Wedding Hashtag
A4: Taylor | B4: Jordan | C4: 46552 | D4: #TaylorAndJordan2026
A6: Wedding Photo Placeholder | E6: HOW TO USE THIS PLANNER
A7: [ Insert your favorite photo here: Insert > Image > Cell ] | E7: 1. Fill in your names, wedding date, and hashtag above.
E8: 2. Start on the Dashboard tab to see your planning snapshot.
E9: 3. Work through the Wedding Checklist tab by timeframe.
E10: 4. Add vendors on the Vendor Selection tab. Mark Final Yes and enter the Amount to auto fill your Budget.
E11: 5. Add guests on the Guest List tab. RSVPs sync automatically to your Seating Plan.
E12: 6. Every dropdown list can be edited on the hidden Lists tab.
E13: 7. Tabs with colored banners are organized by wedding planning category. Use the table of contents below to jump to any tab.
E14: 8. Video tutorial: [insert your tutorial link here]
A17: TABLE OF CONTENTS
A18: 1. Dashboard | C18: 18. Aisle Order
A19: 2. Smart Calendar | C19: 19. Wedding Party Gifts
A20: 3. Wedding Checklist | C20: 20. Moodboard
A21: 4. Wedding Itinerary | C21: 21. Decor Inventory
A22: 5. Wedding Activities | C22: 22. Flower Arrangements
A23: 6. Music Planner | C23: 23. Attire and Makeup
A24: 7. Packing List | C24: 24. Accommodation
A25: 8. Wedding Budget | C25: 25. Transportation
A26: 9. Vendor Selection | C26: 26. Stationery Checklist
A27: 10. Venue Comparison | C27: 27. Save the Date
A28: 11. Food and Drinks | C28: 28. Engagement Party
A29: 12. Photo and Video Shot List | C29: 29. Bridal Shower
... A32: 15. Rehearsal Dinner Seating | C32: 32. Gifts and Thank You
A33: 16. Wedding Registry
A34: 17. Wedding Party

Sheet Dashboard
A1: WEDDING DASHBOARD
A3: ='Get Started'!$A$4&" & "&'Get Started'!$B$4 -> Taylor & Jordan | D3: DAYS UNTIL THE WEDDING | G3: WEDDING DATE | I3: [ Wedding photo placeholder ]
D4: =DATEDIF(TODAY(),'Get Started'!$C$4,"d") -> 300 | G4: ='Get Started'!$C$4 -> 46552 | P4: Checklist | Q4: Value
P5: Done | Q5: =COUNTIFS('Wedding Checklist'!A5:A855,TRUE()) -> 0
P6: Remaining | Q6: =COUNTIFS('Wedding Checklist'!A5:A855,FALSE()) -> 851
A8: WEDDING BUDGET | C8: TOTAL SPENT | E8: LEFT TO SPEND | G8: VENDOR PAYMENTS LEFT | P8: Bride | Q8: =COUNTIFS('Guest List'!B7:B206,"Bride") -> 2
A9: ='Wedding Budget'!A4 -> 21000 | C9: ='Wedding Budget'!E4 -> 17900 | E9: ='Wedding Budget'!G4 -> 3100 | G9: ='Wedding Budget'!I4 -> 1600 | P9: Groom | Q9: =COUNTIFS('Guest List'!B7:B206,"Groom") -> 2
P10: Both | Q10: =COUNTIFS('Guest List'!B7:B206,"Both") -> 2
A11: CONFIRMED GUESTS | C11: CONFIRMED AND SEATED | E11: TENTATIVE SEATS | G11: REMAINING SEATS
A12: ='Guest List'!G4 -> 2 | C12: ='Reception Seating Plan'!E4 -> 0 | E12: ='Reception Seating Plan'!G4 -> 2 | G12: ='Reception Seating Plan'!I4 -> 80 | P12: STD Sent | Q12: ='Guest List'!C4 -> 6
P13: STD Not Sent | Q13: ='Guest List'!A4-'Guest List'!C4 -> 0
A14: CHECKLIST PROGRESS
P15: Invites Sent | Q15: ='Guest List'!E4 -> 6
P16: Invites Not Sent | Q16: ='Guest List'!A4-'Guest List'!E4 -> 0
P18: Attire Status | Q18: Count
P19: Not Started | Q19: =COUNTIFS('Wedding Party'!G$9:G$60,P19) -> 20
P20: Ordered | Q20: =COUNTIFS('Wedding Party'!G$9:G$60,P20) -> 0
P21: Received | Q21: =COUNTIFS('Wedding Party'!G$9:G$60,P21) -> 0
P22: Fitting Scheduled | Q22: =COUNTIFS('Wedding Party'!G$9:G$60,P22) -> 0
P23: Alterations Needed | Q23: =COUNTIFS('Wedding Party'!G$9:G$60,P23) -> 0
P24: Ready | Q24: =COUNTIFS('Wedding Party'!G$9:G$60,P24) -> 0
A64: TODAY | F64: PROGRESS RATIOS
A65: Checklist items due today | C65: =COUNTIFS('Wedding Checklist'!C5:C855,TODAY(),'Wedding Checklist'!A5:A855,FALSE()) -> 0 | F65: Vendor Selection Progress | I65: ='Vendor Selection'!A4 -> 0.6
A66: Deadlines due today | C66: =COUNTIFS('Wedding Budget'!C36:C75,TODAY()) -> 0 | F66: Wedding Party Confirmation | I66: =IFERROR(COUNTIF('Wedding Party'!A8:A60,TRUE())/COUNTA('Wedding Party'!B8:B60),0) -> 0.66666667
F67: Thank You Sent Ratio | I67: =IFERROR(COUNTIF('Gifts and Thank You'!D8:D400,TRUE())/COUNTA('Gifts and Thank You'!A8:A400),0) -> 0

Sheet Smart Calendar
A1: SMART CALENDAR
A3: Month | B3: August | C3: Year | D3: 2026
B4: Budget | C4: Checklist | D4: Important Dates | E4: Stationery | F4: Dance Lessons
A5: SHOW ON CALENDAR: | B5: =TRUE() -> 1 | C5: =TRUE() -> 1 | D5: =TRUE() -> 1 | E5: =TRUE() -> 1 | F5: =TRUE() -> 1
A7: LEGEND: | B7: Due Today | C7: Overdue | D7: Due Later
A9: Sun | B9: Mon | C9: Tue | D9: Wed | E9: Thu | F9: Fri | G9: Sat
A10: =DATE($D$3,MATCH($B$3,MonthNames,0),1)-WEEKDAY(DATE($D$3,MATCH($B$3,MonthNames,0),1))+0+1 -> 46229 | B10: =DATE($D$3,MATCH($B$3,MonthNames,0),1)-WEEKDAY(DATE($D$3,MATCH($B$3,MonthNames,0),1))+1+1 -> 46230 | C10: =DATE($D$3,MATCH($B$3,MonthNames,0),1)-WEEKDAY(DATE($D$3,MATCH($B$3,MonthNames,0),1))+2+1 -> 46231 | D10: =DATE($D$3,MATCH($B$3,MonthNames,0),1)-WEEKDAY(DATE($D$3,MATCH($B$3,MonthNames,0),1))+3+1 -> 46232 | E10: =DATE($D$3,MATCH($B$3,MonthNames,0),1)-WEEKDAY(DATE($D$3,MATCH($B$3,MonthNames,0),1))+4+1 -> 46233 | F10: =DATE($D$3,MATCH($B$3,MonthNames,0),1)-WEEKDAY(DATE($D$3,MATCH($B$3,MonthNames,0),1))+5+1 -> 46234 | G10: =DATE($D$3,MATCH($B$3,MonthNames,0),1)-WEEKDAY(DATE($D$3,MATCH($B$3,MonthNames,0),1))+6+1 -> 46235
A11: =TRIM(IF(AND($C5,COUNTIFS('Wedding Checklist'!$C$5:$C$855,A10,'Wedding Checklist'!$A$5:$A$855,FALSE())>0),COUNTIFS('Wedding Checklist'!$C$5:$C$855,A10,'Wedding Checklist'!$A$5:$A$855,FALSE())&" checklist item(s)"&CHAR(10),"")&IF(AND($B5,COUNTIFS('Wedding Budget'!$C$36:$C$75,A10)>0),COUNTIFS('Wedding Budget'!$C$36:$C$75,A10)&" payment(s) due"&CHAR(10),"")) | B11: =TRIM(IF(AND($C5,COUNTIFS('Wedding Checklist'!$C$5:$C$855,B10,'Wedding Checklist'!$A$5:$A$855,FALSE())>0),COUNTIFS('Wedding Checklist'!$C$5:$C$855,B10,'Wedding Checklist'!$A$5:$A$855,FALSE())&" checklist item(s)"&CHAR(10),"")&IF(AND($B5,COUNTIFS('Wedding Budget'!$C$36:$C$75,B10)>0),COUNTIFS('Wedding Budget'!$C$36:$C$75,B10)&" payment(s) due"&CHAR(10),"")) | C11: =TRIM(IF(AND($C5,COUNTIFS('Wedding Checklist'!$C$5:$C$855,C10,'Wedding Checklist'!$A$5:$A$855,FALSE())>0),COUNTIFS('Wedding Checklist'!$C$5:$C$855,C10,'Wedding Checklist'!$A$5:$A$855,FALSE())&" checklist item(s)"&CHAR(10),"")&IF(AND($B5,COUNTIFS('Wedding Budget'!$C$36:$C$75,C10)>0),COUNTIFS('Wedding Budget'!$C$36:$C$75,C10)&" payment(s) due"&CHAR(10),"")) | D11: =TRIM(IF(AND($C5,COUNTIFS('Wedding Checklist'!$C$5:$C$855,D10,'Wedding Checklist'!$A$5:$A$855,FALSE())>0),COUNTIFS('Wedding Checklist'!$C$5:$C$855,D10,'Wedding Checklist'!$A$5:$A$855,FALSE())&" checklist item(s)"&CHAR(10),"")&IF(AND($B5,COUNTIFS('Wedding Budget'!$C$36:$C$75,D10)>0),COUNTIFS('Wedding Budget'!$C$36:$C$75,D10)&" payment(s) due"&CHAR(10),"")) | E11: =TRIM(IF(AND($C5,COUNTIFS('Wedding Checklist'!$C$5:$C$855,E10,'Wedding Checklist'!$A$5:$A$855,FALSE())>0),COUNTIFS('Wedding Checklist'!$C$5:$C$855,E10,'Wedding Checklist'!$A$5:$A$855,FALSE())&" checklist item(s)"&CHAR(10),"")&IF(AND($B5,COUNTIFS('Wedding Budget'!$C$36:$C$75,E10)>0),COUNTIFS('Wedding Budget'!$C$36:$C$75,E10)&" payment(s) due"&CHAR(10),"")) | F11: =TRIM(IF(AND($C5,COUNTIFS('Wedding Checklist'!$C$5:$C$855,F10,'Wedding Checklist'!$A$5:$A$855,FALSE())>0),COUNTIFS('Wedding Checklist'!$C$5:$C$855,F10,'Wedding Checklist'!$A$5:$A$855,FALSE())&" checklist item(s)"&CHAR(10),"")&IF(AND($B5,COUNTIFS('Wedding Budget'!$C$36:$C$75,F10)>0),COUNTIFS('Wedding Budget'!$C$36:$C$75,F10)&" payment(s) due"&CHAR(10),"")) | G11: =TRIM(IF(AND($C5,COUNTIFS('Wedding Checklist'!$C$5:$C$855,G10,'Wedding Checklist'!$A$5:$A$855,FALSE())>0),COUNTIFS('Wedding Checklist'!$C$5:$C$855,G10,'Wedding Checklist'!$A$5:$A$855,FALSE())&" checklist item(s)"&CHAR(10),"")&IF(AND($B5,COUNTIFS('Wedding Budget'!$C$36:$C$75,G10)>0),COUNTIFS('Wedding Budget'!$C$36:$C$75,G10)&" payment(s) due"&CHAR(10),""))
A13: =DATE($D$3,MATCH($B$3,MonthNames,0),1)-WEEKDAY(DATE($D$3,MATCH($B$3,MonthNames,0),1))+7+1 -> 46236 | B13: =DATE($D$3,MATCH($B$3,MonthNames,0),1)-WEEKDAY(DATE($D$3,MATCH($B$3,MonthNames,0),1))+8+1 -> 46237 | C13: =DATE($D$3,MATCH($B$3,MonthNames,0),1)-WEEKDAY(DATE($D$3,MATCH($B$3,MonthNames,0),1))+9+1 -> 46238 | D13: =DATE($D$3,MATCH($B$3,MonthNames,0),1)-WEEKDAY(DATE($D$3,MATCH($B$3,MonthNames,0),1))+10+1 -> 46239 | E13: =DATE($D$3,MATCH($B$3,MonthNames,0),1)-WEEKDAY(DATE($D$3,MATCH($B$3,MonthNames,0),1))+11+1 -> 46240 | F13: =DATE($D$3,MATCH($B$3,MonthNames,0),1)-WEEKDAY(DATE($D$3,MATCH($B$3,MonthNames,0),1))+12+1 -> 46241 | G13: =DATE($D$3,MATCH($B$3,MonthNames,0),1)-WEEKDAY(DATE($D$3,MATCH($B$3,MonthNames,0),1))+13+1 -> 46242
A14: =TRIM(IF(AND($C5,COUNTIFS('Wedding Checklist'!$C$5:$C$855,A13,'Wedding Checklist'!$A$5:$A$855,FALSE())>0),COUNTIFS('Wedding Checklist'!$C$5:$C$855,A13,'Wedding Checklist'!$A$5:$A$855,FALSE())&" checklist item(s)"&CHAR(10),"")&IF(AND($B5,COUNTIFS('Wedding Budget'!$C$36:$C$75,A13)>0),COUNTIFS('Wedding Budget'!$C$36:$C$75,A13)&" payment(s) due"&CHAR(10),"")) | B14: =TRIM(IF(AND($C5,COUNTIFS('Wedding Checklist'!$C$5:$C$855,B13,'Wedding Checklist'!$A$5:$A$855,FALSE())>0),COUNTIFS('Wedding Checklist'!$C$5:$C$855,B13,'Wedding Checklist'!$A$5:$A$855,FALSE())&" checklist item(s)"&CHAR(10),"")&IF(AND($B5,COUNTIFS('Wedding Budget'!$C$36:$C$75,B13)>0),COUNTIFS('Wedding Budget'!$C$36:$C$75,B13)&" payment(s) due"&CHAR(10),"")) | C14: =TRIM(IF(AND($C5,COUNTIFS('Wedding Checklist'!$C$5:$C$855,C13,'Wedding Checklist'!$A$5:$A$855,FALSE())>0),COUNTIFS('Wedding Checklist'!$C$5:$C$855,C13,'Wedding Checklist'!$A$5:$A$855,FALSE())&" checklist item(s)"&CHAR(10),"")&IF(AND($B5,COUNTIFS('Wedding Budget'!$C$36:$C$75,C13)>0),COUNTIFS('Wedding Budget'!$C$36:$C$75,C13)&" payment(s) due"&CHAR(10),"")) | D14: =TRIM(IF(AND($C5,COUNTIFS('Wedding Checklist'!$C$5:$C$855,D13,'Wedding Checklist'!$A$5:$A$855,FALSE())>0),COUNTIFS('Wedding Checklist'!$C$5:$C$855,D13,'Wedding Checklist'!$A$5:$A$855,FALSE())&" checklist item(s)"&CHAR(10),"")&IF(AND($B5,COUNTIFS('Wedding Budget'!$C$36:$C$75,D13)>0),COUNTIFS('Wedding Budget'!$C$36:$C$75,D13)&" payment(s) due"&CHAR(10),"")) | E14: =TRIM(IF(AND($C5,COUNTIFS('Wedding Checklist'!$C$5:$C$855,E13,'Wedding Checklist'!$A$5:$A$855,FALSE())>0),COUNTIFS('Wedding Checklist'!$C$5:$C$855,E13,'Wedding Checklist'!$A$5:$A$855,FALSE())&" checklist item(s)"&CHAR(10),"")&IF(AND($B5,COUNTIFS('Wedding Budget'!$C$36:$C$75,E13)>0),COUNTIFS('Wedding Budget'!$C$36:$C$75,E13)&" payment(s) due"&CHAR(10),"")) | F14: =TRIM(IF(AND($C5,COUNTIFS('Wedding Checklist'!$C$5:$C$855,F13,'Wedding Checklist'!$A$5:$A$855,FALSE())>0),COUNTIFS('Wedding Checklist'!$C$5:$C$855,F13,'Wedding Checklist'!$A$5:$A$855,FALSE())&" checklist item(s)"&CHAR(10),"")&IF(AND($B5,COUNTIFS('Wedding Budget'!$C$36:$C$75,F13)>0),COUNTIFS('Wedding Budget'!$C$36:$C$75,F13)&" payment(s) due"&CHAR(10),"")) | G14: =TRIM(IF(AND($C5,COUNTIFS('Wedding Checklist'!$C$5:$C$855,G13,'Wedding Checklist'!$A$5:$A$855,FALSE())>0),COUNTIFS('Wedding Checklist'!$C$5:$C$855,G13,'Wedding Checklist'!$A$5:$A$855,FALSE())&" checklist item(s)"&CHAR(10),"")&IF(AND($B5,COUNTIFS('Wedding Budget'!$C$36:$C$75,G13)>0),COUNTIFS('Wedding Budget'!$C$36:$C$75,G13)&" payment(s) due"&CHAR(10),""))
A16: =DATE($D$3,MATCH($B$3,MonthNames,0),1)-WEEKDAY(DATE($D$3,MATCH($B$3,MonthNames,0),1))+14+1 -> 46243 | B16: =DATE($D$3,MATCH($B$3,MonthNames,0),1)-WEEKDAY(DATE($D$3,MATCH($B$3,MonthNames,0),1))+15+1 -> 46244 | C16: =DATE($D$3,MATCH($B$3,MonthNames,0),1)-WEEKDAY(DATE($D$3,MATCH($B$3,MonthNames,0),1))+16+1 -> 46245 | D16: =DATE($D$3,MATCH($B$3,MonthNames,0),1)-WEEKDAY(DATE($D$3,MATCH($B$3,MonthNames,0),1))+17+1 -> 46246 | E16: =DATE($D$3,MATCH($B$3,MonthNames,0),1)-WEEKDAY(DATE($D$3,MATCH($B$3,MonthNames,0),1))+18+1 -> 46247 | F16: =DATE($D$3,MATCH($B$3,MonthNames,0),1)-WEEKDAY(DATE($D$3,MATCH($B$3,MonthNames,0),1))+19+1 -> 46248 | G16: =DATE($D$3,MATCH($B$3,MonthNames,0),1)-WEEKDAY(DATE($D$3,MATCH($B$3,MonthNames,0),1))+20+1 -> 46249
A17: =TRIM(IF(AND($C5,COUNTIFS('Wedding Checklist'!$C$5:$C$855,A16,'Wedding Checklist'!$A$5:$A$855,FALSE())>0),COUNTIFS('Wedding Checklist'!$C$5:$C$855,A16,'Wedding Checklist'!$A$5:$A$855,FALSE())&" checklist item(s)"&CHAR(10),"")&IF(AND($B5,COUNTIFS('Wedding Budget'!$C$36:$C$75,A16)>0),COUNTIFS('Wedding Budget'!$C$36:$C$75,A16)&" payment(s) due"&CHAR(10),"")) | B17: =TRIM(IF(AND($C5,COUNTIFS('Wedding Checklist'!$C$5:$C$855,B16,'Wedding Checklist'!$A$5:$A$855,FALSE())>0),COUNTIFS('Wedding Checklist'!$C$5:$C$855,B16,'Wedding Checklist'!$A$5:$A$855,FALSE())&" checklist item(s)"&CHAR(10),"")&IF(AND($B5,COUNTIFS('Wedding Budget'!$C$36:$C$75,B16)>0),COUNTIFS('Wedding Budget'!$C$36:$C$75,B16)&" payment(s) due"&CHAR(10),"")) | C17: =TRIM(IF(AND($C5,COUNTIFS('Wedding Checklist'!$C$5:$C$855,C16,'Wedding Checklist'!$A$5:$A$855,FALSE())>0),COUNTIFS('Wedding Checklist'!$C$5:$C$855,C16,'Wedding Checklist'!$A$5:$A$855,FALSE())&" checklist item(s)"&CHAR(10),"")&IF(AND($B5,COUNTIFS('Wedding Budget'!$C$36:$C$75,C16)>0),COUNTIFS('Wedding Budget'!$C$36:$C$75,C16)&" payment(s) due"&CHAR(10),"")) | D17: =TRIM(IF(AND($C5,COUNTIFS('Wedding Checklist'!$C$5:$C$855,D16,'Wedding Checklist'!$A$5:$A$855,FALSE())>0),COUNTIFS('Wedding Checklist'!$C$5:$C$855,D16,'Wedding Checklist'!$A$5:$A$855,FALSE())&" checklist item(s)"&CHAR(10),"")&IF(AND($B5,COUNTIFS('Wedding Budget'!$C$36:$C$75,D16)>0),COUNTIFS('Wedding Budget'!$C$36:$C$75,D16)&" payment(s) due"&CHAR(10),"")) | E17: =TRIM(IF(AND($C5,COUNTIFS('Wedding Checklist'!$C$5:$C$855,E16,'Wedding Checklist'!$A$5:$A$855,FALSE())>0),COUNTIFS('Wedding Checklist'!$C$5:$C$855,E16,'Wedding Checklist'!$A$5:$A$855,FALSE())&" checklist item(s)"&CHAR(10),"")&IF(AND($B5,COUNTIFS('Wedding Budget'!$C$36:$C$75,E16)>0),COUNTIFS('Wedding Budget'!$C$36:$C$75,E16)&" payment(s) due"&CHAR(10),"")) | F17: =TRIM(IF(AND($C5,COUNTIFS('Wedding Checklist'!$C$5:$C$855,F16,'Wedding Checklist'!$A$5:$A$855,FALSE())>0),COUNTIFS('Wedding Checklist'!$C$5:$C$855,F16,'Wedding Checklist'!$A$5:$A$855,FALSE())&" checklist item(s)"&CHAR(10),"")&IF(AND($B5,COUNTIFS('Wedding Budget'!$C$36:$C$75,F16)>0),COUNTIFS('Wedding Budget'!$C$36:$C$75,F16)&" payment(s) due"&CHAR(10),"")) | G17: =TRIM(IF(AND($C5,COUNTIFS('Wedding Checklist'!$C$5:$C$855,G16,'Wedding Checklist'!$A$5:$A$855,FALSE())>0),COUNTIFS('Wedding Checklist'!$C$5:$C$855,G16,'Wedding Checklist'!$A$5:$A$855,FALSE())&" checklist item(s)"&CHAR(10),"")&IF(AND($B5,COUNTIFS('Wedding Budget'!$C$36:$C$75,G16)>0),COUNTIFS('Wedding Budget'!$C$36:$C$75,G16)&" payment(s) due"&CHAR(10),""))
A19: =DATE($D$3,MATCH($B$3,MonthNames,0),1)-WEEKDAY(DATE($D$3,MATCH($B$3,MonthNames,0),1))+21+1 -> 46250 | B19: =DATE($D$3,MATCH($B$3,MonthNames,0),1)-WEEKDAY(DATE($D$3,MATCH($B$3,MonthNames,0),1))+22+1 -> 46251 | C19: =DATE($D$3,MATCH($B$3,MonthNames,0),1)-WEEKDAY(DATE($D$3,MATCH($B$3,MonthNames,0),1))+23+1 -> 46252 | D19: =DATE($D$3,MATCH($B$3,MonthNames,0),1)-WEEKDAY(DATE($D$3,MATCH($B$3,MonthNames,0),1))+24+1 -> 46253 | E19: =DATE($D$3,MATCH($B$3,MonthNames,0),1)-WEEKDAY(DATE($D$3,MATCH($B$3,MonthNames,0),1))+25+1 -> 46254 | F19: =DATE($D$3,MATCH($B$3,MonthNames,0),1)-WEEKDAY(DATE($D$3,MATCH($B$3,MonthNames,0),1))+26+1 -> 46255 | G19: =DATE($D$3,MATCH($B$3,MonthNames,0),1)-WEEKDAY(DATE($D$3,MATCH($B$3,MonthNames,0),1))+27+1 -> 46256
A20: =TRIM(IF(AND($C5,COUNTIFS('Wedding Checklist'!$C$5:$C$855,A19,'Wedding Checklist'!$A$5:$A$855,FALSE())>0),COUNTIFS('Wedding Checklist'!$C$5:$C$855,A19,'Wedding Checklist'!$A$5:$A$855,FALSE())&" checklist item(s)"&CHAR(10),"")&IF(AND($B5,COUNTIFS('Wedding Budget'!$C$36:$C$75,A19)>0),COUNTIFS('Wedding Budget'!$C$36:$C$75,A19)&" payment(s) due"&CHAR(10),"")) | B20: =TRIM(IF(AND($C5,COUNTIFS('Wedding Checklist'!$C$5:$C$855,B19,'Wedding Checklist'!$A$5:$A$855,FALSE())>0),COUNTIFS('Wedding Checklist'!$C$5:$C$855,B19,'Wedding Checklist'!$A$5:$A$855,FALSE())&" checklist item(s)"&CHAR(10),"")&IF(AND($B5,COUNTIFS('Wedding Budget'!$C$36:$C$75,B19)>0),COUNTIFS('Wedding Budget'!$C$36:$C$75,B19)&" payment(s) due"&CHAR(10),"")) | C20: =TRIM(IF(AND($C5,COUNTIFS('Wedding Checklist'!$C$5:$C$855,C19,'Wedding Checklist'!$A$5:$A$855,FALSE())>0),COUNTIFS('Wedding Checklist'!$C$5:$C$855,C19,'Wedding Checklist'!$A$5:$A$855,FALSE())&" checklist item(s)"&CHAR(10),"")&IF(AND($B5,COUNTIFS('Wedding Budget'!$C$36:$C$75,C19)>0),COUNTIFS('Wedding Budget'!$C$36:$C$75,C19)&" payment(s) due"&CHAR(10),"")) | D20: =TRIM(IF(AND($C5,COUNTIFS('Wedding Checklist'!$C$5:$C$855,D19,'Wedding Checklist'!$A$5:$A$855,FALSE())>0),COUNTIFS('Wedding Checklist'!$C$5:$C$855,D19,'Wedding Checklist'!$A$5:$A$855,FALSE())&" checklist item(s)"&CHAR(10),"")&IF(AND($B5,COUNTIFS('Wedding Budget'!$C$36:$C$75,D19)>0),COUNTIFS('Wedding Budget'!$C$36:$C$75,D19)&" payment(s) due"&CHAR(10),"")) | E20: =TRIM(IF(AND($C5,COUNTIFS('Wedding Checklist'!$C$5:$C$855,E19,'Wedding Checklist'!$A$5:$A$855,FALSE())>0),COUNTIFS('Wedding Checklist'!$C$5:$C$855,E19,'Wedding Checklist'!$A$5:$A$855,FALSE())&" checklist item(s)"&CHAR(10),"")&IF(AND($B5,COUNTIFS('Wedding Budget'!$C$36:$C$75,E19)>0),COUNTIFS('Wedding Budget'!$C$36:$C$75,E19)&" payment(s) due"&CHAR(10),"")) | F20: =TRIM(IF(AND($C5,COUNTIFS('Wedding Checklist'!$C$5:$C$855,F19,'Wedding Checklist'!$A$5:$A$855,FALSE())>0),COUNTIFS('Wedding Checklist'!$C$5:$C$855,F19,'Wedding Checklist'!$A$5:$A$855,FALSE())&" checklist item(s)"&CHAR(10),"")&IF(AND($B5,COUNTIFS('Wedding Budget'!$C$36:$C$75,F19)>0),COUNTIFS('Wedding Budget'!$C$36:$C$75,F19)&" payment(s) due"&CHAR(10),"")) | G20: =TRIM(IF(AND($C5,COUNTIFS('Wedding Checklist'!$C$5:$C$855,G19,'Wedding Checklist'!$A$5:$A$855,FALSE())>0),COUNTIFS('Wedding Checklist'!$C$5:$C$855,G19,'Wedding Checklist'!$A$5:$A$855,FALSE())&" checklist item(s)"&CHAR(10),"")&IF(AND($B5,COUNTIFS('Wedding Budget'!$C$36:$C$75,G19)>0),COUNTIFS('Wedding Budget'!$C$36:$C$75,G19)&" payment(s) due"&CHAR(10),""))
A22: =DATE($D$3,MATCH($B$3,MonthNames,0),1)-WEEKDAY(DATE($D$3,MATCH($B$3,MonthNames,0),1))+28+1 -> 46257 | B22: =DATE($D$3,MATCH($B$3,MonthNames,0),1)-WEEKDAY(DATE($D$3,MATCH($B$3,MonthNames,0),1))+29+1 -> 46258 | C22: =DATE($D$3,MATCH($B$3,MonthNames,0),1)-WEEKDAY(DATE($D$3,MATCH($B$3,MonthNames,0),1))+30+1 -> 46259 | D22: =DATE($D$3,MATCH($B$3,MonthNames,0),1)-WEEKDAY(DATE($D$3,MATCH($B$3,MonthNames,0),1))+31+1 -> 46260 | E22: =DATE($D$3,MATCH($B$3,MonthNames,0),1)-WEEKDAY(DATE($D$3,MATCH($B$3,MonthNames,0),1))+32+1 -> 46261 | F22: =DATE($D$3,MATCH($B$3,MonthNames,0),1)-WEEKDAY(DATE($D$3,MATCH($B$3,MonthNames,0),1))+33+1 -> 46262 | G22: =DATE($D$3,MATCH($B$3,MonthNames,0),1)-WEEKDAY(DATE($D$3,MATCH($B$3,MonthNames,0),1))+34+1 -> 46263
A23: =TRIM(IF(AND($C5,COUNTIFS('Wedding Checklist'!$C$5:$C$855,A22,'Wedding Checklist'!$A$5:$A$855,FALSE())>0),COUNTIFS('Wedding Checklist'!$C$5:$C$855,A22,'Wedding Checklist'!$A$5:$A$855,FALSE())&" checklist item(s)"&CHAR(10),"")&IF(AND($B5,COUNTIFS('Wedding Budget'!$C$36:$C$75,A22)>0),COUNTIFS('Wedding Budget'!$C$36:$C$75,A22)&" payment(s) due"&CHAR(10),"")) | B23: =TRIM(IF(AND($C5,COUNTIFS('Wedding Checklist'!$C$5:$C$855,B22,'Wedding Checklist'!$A$5:$A$855,FALSE())>0),COUNTIFS('Wedding Checklist'!$C$5:$C$855,B22,'Wedding Checklist'!$A$5:$A$855,FALSE())&" checklist item(s)"&CHAR(10),"")&IF(AND($B5,COUNTIFS('Wedding Budget'!$C$36:$C$75,B22)>0),COUNTIFS('Wedding Budget'!$C$36:$C$75,B22)&" payment(s) due"&CHAR(10),"")) | C23: =TRIM(IF(AND($C5,COUNTIFS('Wedding Checklist'!$C$5:$C$855,C22,'Wedding Checklist'!$A$5:$A$855,FALSE())>0),COUNTIFS('Wedding Checklist'!$C$5:$C$855,C22,'Wedding Checklist'!$A$5:$A$855,FALSE())&" checklist item(s)"&CHAR(10),"")&IF(AND($B5,COUNTIFS('Wedding Budget'!$C$36:$C$75,C22)>0),COUNTIFS('Wedding Budget'!$C$36:$C$75,C22)&" payment(s) due"&CHAR(10),"")) | D23: =TRIM(IF(AND($C5,COUNTIFS('Wedding Checklist'!$C$5:$C$855,D22,'Wedding Checklist'!$A$5:$A$855,FALSE())>0),COUNTIFS('Wedding Checklist'!$C$5:$C$855,D22,'Wedding Checklist'!$A$5:$A$855,FALSE())&" checklist item(s)"&CHAR(10),"")&IF(AND($B5,COUNTIFS('Wedding Budget'!$C$36:$C$75,D22)>0),COUNTIFS('Wedding Budget'!$C$36:$C$75,D22)&" payment(s) due"&CHAR(10),"")) | E23: =TRIM(IF(AND($C5,COUNTIFS('Wedding Checklist'!$C$5:$C$855,E22,'Wedding Checklist'!$A$5:$A$855,FALSE())>0),COUNTIFS('Wedding Checklist'!$C$5:$C$855,E22,'Wedding Checklist'!$A$5:$A$855,FALSE())&" checklist item(s)"&CHAR(10),"")&IF(AND($B5,COUNTIFS('Wedding Budget'!$C$36:$C$75,E22)>0),COUNTIFS('Wedding Budget'!$C$36:$C$75,E22)&" payment(s) due"&CHAR(10),"")) | F23: =TRIM(IF(AND($C5,COUNTIFS('Wedding Checklist'!$C$5:$C$855,F22,'Wedding Checklist'!$A$5:$A$855,FALSE())>0),COUNTIFS('Wedding Checklist'!$C$5:$C$855,F22,'Wedding Checklist'!$A$5:$A$855,FALSE())&" checklist item(s)"&CHAR(10),"")&IF(AND($B5,COUNTIFS('Wedding Budget'!$C$36:$C$75,F22)>0),COUNTIFS('Wedding Budget'!$C$36:$C$75,F22)&" payment(s) due"&CHAR(10),"")) | G23: =TRIM(IF(AND($C5,COUNTIFS('Wedding Checklist'!$C$5:$C$855,G22,'Wedding Checklist'!$A$5:$A$855,FALSE())>0),COUNTIFS('Wedding Checklist'!$C$5:$C$855,G22,'Wedding Checklist'!$A$5:$A$855,FALSE())&" checklist item(s)"&CHAR(10),"")&IF(AND($B5,COUNTIFS('Wedding Budget'!$C$36:$C$75,G22)>0),COUNTIFS('Wedding Budget'!$C$36:$C$75,G22)&" payment(s) due"&CHAR(10),""))
A25: =DATE($D$3,MATCH($B$3,MonthNames,0),1)-WEEKDAY(DATE($D$3,MATCH($B$3,MonthNames,0),1))+35+1 -> 46264 | B25: =DATE($D$3,MATCH($B$3,MonthNames,0),1)-WEEKDAY(DATE($D$3,MATCH($B$3,MonthNames,0),1))+36+1 -> 46265 | C25: =DATE($D$3,MATCH($B$3,MonthNames,0),1)-WEEKDAY(DATE($D$3,MATCH($B$3,MonthNames,0),1))+37+1 -> 46266 | D25: =DATE($D$3,MATCH($B$3,MonthNames,0),1)-WEEKDAY(DATE($D$3,MATCH($B$3,MonthNames,0),1))+38+1 -> 46267 | E25: =DATE($D$3,MATCH($B$3,MonthNames,0),1)-WEEKDAY(DATE($D$3,MATCH($B$3,MonthNames,0),1))+39+1 -> 46268 | F25: =DATE($D$3,MATCH($B$3,MonthNames,0),1)-WEEKDAY(DATE($D$3,MATCH($B$3,MonthNames,0),1))+40+1 -> 46269 | G25: =DATE($D$3,MATCH($B$3,MonthNames,0),1)-WEEKDAY(DATE($D$3,MATCH($B$3,MonthNames,0),1))+41+1 -> 46270
A26: =TRIM(IF(AND($C5,COUNTIFS('Wedding Checklist'!$C$5:$C$855,A25,'Wedding Checklist'!$A$5:$A$855,FALSE())>0),COUNTIFS('Wedding Checklist'!$C$5:$C$855,A25,'Wedding Checklist'!$A$5:$A$855,FALSE())&" checklist item(s)"&CHAR(10),"")&IF(AND($B5,COUNTIFS('Wedding Budget'!$C$36:$C$75,A25)>0),COUNTIFS('Wedding Budget'!$C$36:$C$75,A25)&" payment(s) due"&CHAR(10),"")) | B26: =TRIM(IF(AND($C5,COUNTIFS('Wedding Checklist'!$C$5:$C$855,B25,'Wedding Checklist'!$A$5:$A$855,FALSE())>0),COUNTIFS('Wedding Checklist'!$C$5:$C$855,B25,'Wedding Checklist'!$A$5:$A$855,FALSE())&" checklist item(s)"&CHAR(10),"")&IF(AND($B5,COUNTIFS('Wedding Budget'!$C$36:$C$75,B25)>0),COUNTIFS('Wedding Budget'!$C$36:$C$75,B25)&" payment(s) due"&CHAR(10),"")) | C26: =TRIM(IF(AND($C5,COUNTIFS('Wedding Checklist'!$C$5:$C$855,C25,'Wedding Checklist'!$A$5:$A$855,FALSE())>0),COUNTIFS('Wedding Checklist'!$C$5:$C$855,C25,'Wedding Checklist'!$A$5:$A$855,FALSE())&" checklist item(s)"&CHAR(10),"")&IF(AND($B5,COUNTIFS('Wedding Budget'!$C$36:$C$75,C25)>0),COUNTIFS('Wedding Budget'!$C$36:$C$75,C25)&" payment(s) due"&CHAR(10),"")) | D26: =TRIM(IF(AND($C5,COUNTIFS('Wedding Checklist'!$C$5:$C$855,D25,'Wedding Checklist'!$A$5:$A$855,FALSE())>0),COUNTIFS('Wedding Checklist'!$C$5:$C$855,D25,'Wedding Checklist'!$A$5:$A$855,FALSE())&" checklist item(s)"&CHAR(10),"")&IF(AND($B5,COUNTIFS('Wedding Budget'!$C$36:$C$75,D25)>0),COUNTIFS('Wedding Budget'!$C$36:$C$75,D25)&" payment(s) due"&CHAR(10),"")) | E26: =TRIM(IF(AND($C5,COUNTIFS('Wedding Checklist'!$C$5:$C$855,E25,'Wedding Checklist'!$A$5:$A$855,FALSE())>0),COUNTIFS('Wedding Checklist'!$C$5:$C$855,E25,'Wedding Checklist'!$A$5:$A$855,FALSE())&" checklist item(s)"&CHAR(10),"")&IF(AND($B5,COUNTIFS('Wedding Budget'!$C$36:$C$75,E25)>0),COUNTIFS('Wedding Budget'!$C$36:$C$75,E25)&" payment(s) due"&CHAR(10),"")) | F26: =TRIM(IF(AND($C5,COUNTIFS('Wedding Checklist'!$C$5:$C$855,F25,'Wedding Checklist'!$A$5:$A$855,FALSE())>0),COUNTIFS('Wedding Checklist'!$C$5:$C$855,F25,'Wedding Checklist'!$A$5:$A$855,FALSE())&" checklist item(s)"&CHAR(10),"")&IF(AND($B5,COUNTIFS('Wedding Budget'!$C$36:$C$75,F25)>0),COUNTIFS('Wedding Budget'!$C$36:$C$75,F25)&" payment(s) due"&CHAR(10),"")) | G26: =TRIM(IF(AND($C5,COUNTIFS('Wedding Checklist'!$C$5:$C$855,G25,'Wedding Checklist'!$A$5:$A$855,FALSE())>0),COUNTIFS('Wedding Checklist'!$C$5:$C$855,G25,'Wedding Checklist'!$A$5:$A$855,FALSE())&" checklist item(s)"&CHAR(10),"")&IF(AND($B5,COUNTIFS('Wedding Budget'!$C$36:$C$75,G25)>0),COUNTIFS('Wedding Budget'!$C$36:$C$75,G25)&" payment(s) due"&CHAR(10),""))
A29: IMPORTANT DATES
A30: Task Description | B30: Due Date
A31: Book officiant meeting | B31: ='Get Started'!$C$4+(-300) -> 46252
A32: Order wedding invitations | B32: ='Get Started'!$C$4+(-180) -> 46372
A33: Final dress fitting | B33: ='Get Started'!$C$4+(-30) -> 46522
A34: Marriage license appointment | B34: ='Get Started'!$C$4+(-14) -> 46538
A35: Rehearsal dinner | B35: ='Get Started'!$C$4+(-1) -> 46551

Sheet Wedding Checklist
A1: WEDDING CHECKLIST
A2: Check off each task as you complete it. Due dates are examples, set to guide pacing before the wedding date on the Get Started tab.
A4: Done | B4: Task | C4: Due Date | D4: Assigned To | E4: Priority | F4: Section | H4: PROGRESS BY SECTION
A5: =FALSE() -> 0 | B5: Announce your engagement to family and close friends | C5: ='Get Started'!$C$4-400+-5 -> 46147 | D5: Both | E5: Medium | F5: 12+ Months Before | H5: Section | I5: % Done | J5: Count
A6: =FALSE() -> 0 | B6: Set a realistic wedding budget with your partner | C6: ='Get Started'!$C$4-400+-5 -> 46147 | D6: Both | E6: Medium | F6: 12+ Months Before | H6: 12+ Months Before | I6: =COUNTIFS(A5:A91,TRUE())/COUNTA(B5:B91) -> 0 | J6: =COUNTA(B5:B91) -> 87
A7: =FALSE() -> 0 | B7: Decide who is contributing to the budget and how much | C7: ='Get Started'!$C$4-400+-5 -> 46147 | D7: Both | E7: Medium | F7: 12+ Months Before | H7: 10-12 Months Before | I7: =COUNTIFS(A92:A192,TRUE())/COUNTA(B92:B192) -> 0 | J7: =COUNTA(B92:B192) -> 101
A8: =FALSE() -> 0 | B8: Choose your wedding date (or a short list of dates) | C8: ='Get Started'!$C$4-400+-5 -> 46147 | D8: Both | E8: Medium | F8: 12+ Months Before | H8: 8-10 Months Before | I8: =COUNTIFS(A193:A324,TRUE())/COUNTA(B193:B324) -> 0 | J8: =COUNTA(B193:B324) -> 132
A9: =FALSE() -> 0 | B9: Decide on wedding size (intimate, medium, large) | C9: ='Get Started'!$C$4-400+-5 -> 46147 | D9: Both | E9: Medium | F9: 12+ Months Before | H9: 6-8 Months Before | I9: =COUNTIFS(A325:A421,TRUE())/COUNTA(B325:B421) -> 0 | J9: =COUNTA(B325:B421) -> 97
A10: =FALSE() -> 0 | B10: Create a rough guest list headcount estimate | C10: ='Get Started'!$C$4-400+-5 -> 46147 | D10: Both | E10: Medium | F10: 12+ Months Before | H10: 4-6 Months Before | I10: =COUNTIFS(A422:A513,TRUE())/COUNTA(B422:B513) -> 0 | J10: =COUNTA(B422:B513) -> 92
A11: =FALSE() -> 0 | B11: Discuss and choose a wedding vision, theme, and color palette | C11: ='Get Started'!$C$4-400+-5 -> 46147 | D11: Both | E11: Medium | F11: 12+ Months Before | H11: 2-4 Months Before | I11: =COUNTIFS(A514:A609,TRUE())/COUNTA(B514:B609) -> 0 | J11: =COUNTA(B514:B609) -> 96
A12: =FALSE() -> 0 | B12: Choose the season and general location for the wedding | C12: ='Get Started'!$C$4-400+-5 -> 46147 | D12: Both | E12: Medium | F12: 12+ Months Before | H12: 1 Month Before | I12: =COUNTIFS(A610:A666,TRUE())/COUNTA(B610:B666) -> 0 | J12: =COUNTA(B610:B666) -> 57
A13: =FALSE() -> 0 | B13: Decide whether to hire a wedding planner | C13: ='Get Started'!$C$4-400+-5 -> 46147 | D13: Both | E13: Medium | F13: 12+ Months Before | H13: 2 Weeks Before | I13: =COUNTIFS(A667:A725,TRUE())/COUNTA(B667:B725) -> 0 | J13: =COUNTA(B667:B725) -> 59
A14: =FALSE() -> 0 | B14: Interview and hire a wedding planner if desired | C14: ='Get Started'!$C$4-400+-4 -> 46148 | D14: Both | E14: Medium | F14: 12+ Months Before | H14: 1 Week Before | I14: =COUNTIFS(A726:A772,TRUE())/COUNTA(B726:B772) -> 0 | J14: =COUNTA(B726:B772) -> 47
A15: =FALSE() -> 0 | B15: Start a shared wedding planning binder or spreadsheet | C15: ='Get Started'!$C$4-400+-4 -> 46148 | D15: Both | E15: Medium | F15: 12+ Months Before | H15: 2 Days Before | I15: =COUNTIFS(A773:A791,TRUE())/COUNTA(B773:B791) -> 0 | J15: =COUNTA(B773:B791) -> 19
A16: =FALSE() -> 0 | B16: Create a private wedding email address for vendor communication | C16: ='Get Started'!$C$4-400+-4 -> 46148 | D16: Both | E16: Medium | F16: 12+ Months Before | H16: 1 Day Before | I16: =COUNTIFS(A792:A804,TRUE())/COUNTA(B792:B804) -> 0 | J16: =COUNTA(B792:B804) -> 13
A17: =FALSE() -> 0 | B17: Set up a wedding website | C17: ='Get Started'!$C$4-400+-4 -> 46148 | D17: Both | E17: Medium | F17: 12+ Months Before | H17: Legal Items | I17: =COUNTIFS(A805:A855,TRUE())/COUNTA(B805:B855) -> 0 | J17: =COUNTA(B805:B855) -> 51
A18: =FALSE() -> 0 | B18: Choose a wedding hashtag | C18: ='Get Started'!$C$4-400+-4 -> 46148 | D18: Both | E18: Medium | F18: 12+ Months Before
A19: =FALSE() -> 0 | B19: Draft the full guest list with addresses | C19: ='Get Started'!$C$4-400+-4 -> 46148 | D19: Both | E19: Medium | F19: 12+ Months Before | H19: TASKS REMAINING BY PERSON
A20: =FALSE() -> 0 | B20: Consider a guest list cap and stick to it | C20: ='Get Started'!$C$4-400+-4 -> 46148 | D20: Both | E20: Medium | F20: 12+ Months Before | H20: Bride | I20: =COUNTIFS($D$5:$D$855,H20,$A$5:$A$855,FALSE()) -> 0
A21: =FALSE() -> 0 | B21: Research ceremony and reception venue options | C21: ='Get Started'!$C$4-400+-4 -> 46148 | D21: Both | E21: Medium | F21: 12+ Months Before | H21: Groom | I21: =COUNTIFS($D$5:$D$855,H21,$A$5:$A$855,FALSE()) -> 0
A22: =FALSE() -> 0 | B22: Tour at least 5 potential venues | C22: ='Get Started'!$C$4-400+-4 -> 46148 | D22: Both | E22: Medium | F22: 12+ Months Before | H22: Both | I22: =COUNTIFS($D$5:$D$855,H22,$A$5:$A$855,FALSE()) -> 851
A23: =FALSE() -> 0 | B23: Ask venues about capacity, availability, and included services | C23: ='Get Started'!$C$4-400+-3 -> 46149 | D23: Both | E23: Medium | F23: 12+ Months Before | H23: Wedding Planner | I23: =COUNTIFS($D$5:$D$855,H23,$A$5:$A$855,FALSE()) -> 0
A24: =FALSE() -> 0 | B24: Compare venue costs and what's included in each package | C24: ='Get Started'!$C$4-400+-3 -> 46149 | D24: Both | E24: Medium | F24: 12+ Months Before | H24: Maid of Honor | I24: =COUNTIFS($D$5:$D$855,H24,$A$5:$A$855,FALSE()) -> 0
A25: =FALSE() -> 0 | B25: Book ceremony venue and sign contract | C25: ='Get Started'!$C$4-400+-3 -> 46149 | D25: Both | E25: Medium | F25: 12+ Months Before | H25: Best Man | I25: =COUNTIFS($D$5:$D$855,H25,$A$5:$A$855,FALSE()) -> 0
A26: =FALSE() -> 0 | B26: Book reception venue and sign contract | C26: ='Get Started'!$C$4-400+-3 -> 46149 | D26: Both | E26: Medium | F26: 12+ Months Before | H26: Parent | I26: =COUNTIFS($D$5:$D$855,H26,$A$5:$A$855,FALSE()) -> 0
A27: =FALSE() -> 0 | B27: Pay venue deposit | C27: ='Get Started'!$C$4-400+-3 -> 46149 | D27: Both | E27: Medium | F27: 12+ Months Before | H27: Other | I27: =COUNTIFS($D$5:$D$855,H27,$A$5:$A$855,FALSE()) -> 0
A28: =FALSE() -> 0 | B28: Consider hiring an officiant or asking a friend to get ordained | C28: ='Get Started'!$C$4-400+-3 -> 46149 | D28: Both | E28: Medium | F28: 12+ Months Before
A29: =FALSE() -> 0 | B29: Start researching photographers and browsing portfolios | C29: ='Get Started'!$C$4-400+-3 -> 46149 | D29: Both | E29: Medium | F29: 12+ Months Before
A30: =FALSE() -> 0 | B30: Start researching videographers and browsing reels | C30: ='Get Started'!$C$4-400+-3 -> 46149 | D30: Both | E30: Medium | F30: 12+ Months Before
A31: =FALSE() -> 0 | B31: Start researching wedding planners or day-of coordinators | C31: ='Get Started'!$C$4-400+-2 -> 46150 | D31: Both | E31: Medium | F31: 12+ Months Before
A32: =FALSE() -> 0 | B32: Start a Pinterest or moodboard for overall wedding style | C32: ='Get Started'!$C$4-400+-2 -> 46150 | D32: Both | E32: Medium | F32: 12+ Months Before
A33: =FALSE() -> 0 | B33: Decide on a rough guest count range for catering purposes | C33: ='Get Started'!$C$4-400+-2 -> 46150 | D33: Both | E33: Medium | F33: 12+ Months Before
A34: =FALSE() -> 0 | B34: Research average wedding costs in your area for budgeting | C34: ='Get Started'!$C$4-400+-2 -> 46150 | D34: Both | E34: Medium | F34: 12+ Months Before
A35: =FALSE() -> 0 | B35: Open a dedicated wedding savings account | C35: ='Get Started'!$C$4-400+-2 -> 46150 | D35: Both | E35: Medium | F35: 12+ Months Before
A36: =FALSE() -> 0 | B36: Discuss honeymoon budget separately from wedding budget | C36: ='Get Started'!$C$4-400+-2 -> 46150 | D36: Both | E36: Medium | F36: 12+ Months Before
A37: =FALSE() -> 0 | B37: Ask parents or family about their wishes to be involved | C37: ='Get Started'!$C$4-400+-2 -> 46150 | D37: Both | E37: Medium | F37: 12+ Months Before
A38: =FALSE() -> 0 | B38: Decide on wedding party size and who to ask | C38: ='Get Started'!$C$4-400+-2 -> 46150 | D38: Both | E38: Medium | F38: 12+ Months Before
A39: =FALSE() -> 0 | B39: Draft a wedding party wish list (who you want to ask) | C39: ='Get Started'!$C$4-400+-2 -> 46150 | D39: Both | E39: Medium | F39: 12+ Months Before
A40: =FALSE() -> 0 | B40: Research marriage license requirements in your state | C40: ='Get Started'!$C$4-400+-1 -> 46151 | D40: Both | E40: Medium | F40: 12+ Months Before
A41: =FALSE() -> 0 | B41: Check passport expiration dates if honeymooning abroad | C41: ='Get Started'!$C$4-400+-1 -> 46151 | D41: Both | E41: Medium | F41: 12+ Months Before
A42: =FALSE() -> 0 | B42: Purchase wedding insurance if desired | C42: ='Get Started'!$C$4-400+-1 -> 46151 | D42: Both | E42: Medium | F42: 12+ Months Before
A43: =FALSE() -> 0 | B43: Create a Pinterest board for dress and suit inspiration | C43: ='Get Started'!$C$4-400+-1 -> 46151 | D43: Both | E43: Medium | F43: 12+ Months Before
A44: =FALSE() -> 0 | B44: Research caterers and schedule tastings | C44: ='Get Started'!$C$4-400+-1 -> 46151 | D44: Both | E44: Medium | F44: 12+ Months Before
A45: =FALSE() -> 0 | B45: Book caterer and sign contract | C45: ='Get Started'!$C$4-400+-1 -> 46151 | D45: Both | E45: Medium | F45: 12+ Months Before
A46: =FALSE() -> 0 | B46: Research florists and their portfolios | C46: ='Get Started'!$C$4-400+-1 -> 46151 | D46: Both | E46: Medium | F46: 12+ Months Before
A47: =FALSE() -> 0 | B47: Research DJ and live band options | C47: ='Get Started'!$C$4-400+-1 -> 46151 | D47: Both | E47: Medium | F47: 12+ Months Before
A48: =FALSE() -> 0 | B48: Attend a bridal show for vendor inspiration | C48: ='Get Started'!$C$4-400+0 -> 46152 | D48: Both | E48: Medium | F48: 12+ Months Before
A49: =FALSE() -> 0 | B49: Discuss and decide on wedding style: formal, casual, destination | C49: ='Get Started'!$C$4-400+0 -> 46152 | D49: Both | E49: Medium | F49: 12+ Months Before
A50: =FALSE() -> 0 | B50: Decide on ceremony type: religious, civil, or symbolic | C50: ='Get Started'!$C$4-400+0 -> 46152 | D50: Both | E50: Medium | F50: 12+ Months Before
A51: =FALSE() -> 0 | B51: Research legal requirements for a destination wedding, if applicable | C51: ='Get Started'!$C$4-400+0 -> 46152 | D51: Both | E51: Medium | F51: 12+ Months Before
A52: =FALSE() -> 0 | B52: Start a wedding day timeline outline | C52: ='Get Started'!$C$4-400+0 -> 46152 | D52: Both | E52: Medium | F52: 12+ Months Before
A53: =FALSE() -> 0 | B53: Choose a wedding party gift budget | C53: ='Get Started'!$C$4-400+0 -> 46152 | D53: Both | E53: Medium | F53: 12+ Months Before
A54: =FALSE() -> 0 | B54: Set up a wedding budget spreadsheet by category | C54: ='Get Started'!$C$4-400+0 -> 46152 | D54: Both | E54: Medium | F54: 12+ Months Before
A55: =FALSE() -> 0 | B55: Research average vendor deposit amounts to plan cash flow | C55: ='Get Started'!$C$4-400+0 -> 46152 | D55: Both | E55: Medium | F55: 12+ Months Before
A56: =FALSE() -> 0 | B56: Research Venue options in your area and read reviews | C56: ='Get Started'!$C$4-400+0 -> 46152 | D56: Both | E56: Medium | F56: 12+ Months Before
A57: =FALSE() -> 0 | B57: Research Caterer options in your area and read reviews | C57: ='Get Started'!$C$4-400+1 -> 46153 | D57: Both | E57: Medium | F57: 12+ Months Before
A58: =FALSE() -> 0 | B58: Research Photographer options in your area and read reviews | C58: ='Get Started'!$C$4-400+1 -> 46153 | D58: Both | E58: Medium | F58: 12+ Months Before
A59: =FALSE() -> 0 | B59: Research Videographer options in your area and read reviews | C59: ='Get Started'!$C$4-400+1 -> 46153 | D59: Both | E59: Medium | F59: 12+ Months Before
A60: =FALSE() -> 0 | B60: Research Florist options in your area and read reviews | C60: ='Get Started'!$C$4-400+1 -> 46153 | D60: Both | E60: Medium | F60: 12+ Months Before
A61: =FALSE() -> 0 | B61: Research DJ or Band options in your area and read reviews | C61: ='Get Started'!$C$4-400+1 -> 46153 | D61: Both | E61: Medium | F61: 12+ Months Before
A62: =FALSE() -> 0 | B62: Research Officiant options in your area and read reviews | C62: ='Get Started'!$C$4-400+1 -> 46153 | D62: Both | E62: Medium | F62: 12+ Months Before
A63: =FALSE() -> 0 | B63: Research Rental Company options in your area and read reviews | C63: ='Get Started'!$C$4-400+1 -> 46153 | D63: Both | E63: Medium | F63: 12+ Months Before
A64: =FALSE() -> 0 | B64: Research Decor Stylist options in your area and read reviews | C64: ='Get Started'!$C$4-400+1 -> 46153 | D64: Both | E64: Medium | F64: 12+ Months Before
A65: =FALSE() -> 0 | B65: Research Hair Stylist options in your area and read reviews | C65: ='Get Started'!$C$4-400+1 -> 46153 | D65: Both | E65: Medium | F65: 12+ Months Before
A66: =FALSE() -> 0 | B66: Research Makeup Artist options in your area and read reviews | C66: ='Get Started'!$C$4-400+2 -> 46154 | D66: Both | E66: Medium | F66: 12+ Months Before
A67: =FALSE() -> 0 | B67: Research Transportation Company options in your area and read reviews | C67: ='Get Started'!$C$4-400+2 -> 46154 | D67: Both | E67: Medium | F67: 12+ Months Before
A68: =FALSE() -> 0 | B68: Research Cake Baker options in your area and read reviews | C68: ='Get Started'!$C$4-400+2 -> 46154 | D68: Both | E68: Medium | F68: 12+ Months Before
A69: =FALSE() -> 0 | B69: Research Stationer options in your area and read reviews | C69: ='Get Started'!$C$4-400+2 -> 46154 | D69: Both | E69: Medium | F69: 12+ Months Before
A70: =FALSE() -> 0 | B70: Research Favor Supplier options in your area and read reviews | C70: ='Get Started'!$C$4-400+2 -> 46154 | D70: Both | E70: Medium | F70: 12+ Months Before
A71: =FALSE() -> 0 | B71: Research Lighting Company options in your area and read reviews | C71: ='Get Started'!$C$4-400+2 -> 46154 | D71: Both | E71: Medium | F71: 12+ Months Before
A72: =FALSE() -> 0 | B72: Research Wedding Planner options in your area and read reviews | C72: ='Get Started'!$C$4-400+2 -> 46154 | D72: Both | E72: Medium | F72: 12+ Months Before
A73: =FALSE() -> 0 | B73: Research Photo Booth Company options in your area and read reviews | C73: ='Get Started'!$C$4-400+2 -> 46154 | D73: Both | E73: Medium | F73: 12+ Months Before
A74: =FALSE() -> 0 | B74: Discuss blended family or step-parent involvement, if applicable | C74: ='Get Started'!$C$4-400+3 -> 46155 | D74: Both | E74: Medium | F74: 12+ Months Before
A75: =FALSE() -> 0 | B75: Decide on a guest list policy for plus-ones | C75: ='Get Started'!$C$4-400+3 -> 46155 | D75: Both | E75: Medium | F75: 12+ Months Before
A76: =FALSE() -> 0 | B76: Decide on a policy for children at the wedding | C76: ='Get Started'!$C$4-400+3 -> 46155 | D76: Both | E76: Medium | F76: 12+ Months Before
A77: =FALSE() -> 0 | B77: Research whether your venue requires liability insurance | C77: ='Get Started'!$C$4-400+3 -> 46155 | D77: Both | E77: Medium | F77: 12+ Months Before
A78: =FALSE() -> 0 | B78: Set up a wedding planning shared calendar for both partners | C78: ='Get Started'!$C$4-400+3 -> 46155 | D78: Both | E78: Medium | F78: 12+ Months Before
A79: =FALSE() -> 0 | B79: Discuss and agree on non-negotiable wedding priorities | C79: ='Get Started'!$C$4-400+3 -> 46155 | D79: Both | E79: Medium | F79: 12+ Months Before
A80: =FALSE() -> 0 | B80: Discuss and agree on where to cut costs if needed | C80: ='Get Started'!$C$4-400+3 -> 46155 | D80: Both | E80: Medium | F80: 12+ Months Before
A81: =FALSE() -> 0 | B81: Research off-season or weekday dates for potential savings | C81: ='Get Started'!$C$4-400+3 -> 46155 | D81: Both | E81: Medium | F81: 12+ Months Before
A82: =FALSE() -> 0 | B82: Ask trusted friends for vendor recommendations | C82: ='Get Started'!$C$4-400+3 -> 46155 | D82: Both | E82: Medium | F82: 12+ Months Before
A83: =FALSE() -> 0 | B83: Join online wedding planning communities for advice | C83: ='Get Started'!$C$4-400+4 -> 46156 | D83: Both | E83: Medium | F83: 12+ Months Before
A84: =FALSE() -> 0 | B84: Research local wedding rules and permits for outdoor venues | C84: ='Get Started'!$C$4-400+4 -> 46156 | D84: Both | E84: Medium | F84: 12+ Months Before
A85: =FALSE() -> 0 | B85: Discuss blended religious or cultural ceremony traditions to include | C85: ='Get Started'!$C$4-400+4 -> 46156 | D85: Both | E85: Medium | F85: 12+ Months Before
A86: =FALSE() -> 0 | B86: Create a shared document of must-have wedding traditions | C86: ='Get Started'!$C$4-400+4 -> 46156 | D86: Both | E86: Medium | F86: 12+ Months Before
A87: =FALSE() -> 0 | B87: Research live-streaming options for guests who cannot attend | C87: ='Get Started'!$C$4-400+4 -> 46156 | D87: Both | E87: Medium | F87: 12+ Months Before
A88: =FALSE() -> 0 | B88: Discuss accessibility needs for guests with mobility limitations | C88: ='Get Started'!$C$4-400+4 -> 46156 | D88: Both | E88: Medium | F88: 12+ Months Before
A89: =FALSE() -> 0 | B89: Take engagement photos for save the dates and the wedding website | C89: ='Get Started'!$C$4-400+4 -> 46156 | D89: Both | E89: Medium | F89: 12+ Months Before
A90: =FALSE() -> 0 | B90: Discuss whether to have a unity ceremony element | C90: ='Get Started'!$C$4-400+4 -> 46156 | D90: Both | E90: Medium | F90: 12+ Months Before
A91: =FALSE() -> 0 | B91: Decide on wedding party attire budget responsibility | C91: ='Get Started'!$C$4-400+5 -> 46157 | D91: Both | E91: Medium | F91: 12+ Months Before
A92: =FALSE() -> 0 | B92: Finalize the guest list headcount for venue and catering | C92: ='Get Started'!$C$4-330+-5 -> 46217 | D92: Both | E92: Medium | F92: 10-12 Months Before
A93: =FALSE() -> 0 | B93: Book photographer and sign contract | C93: ='Get Started'!$C$4-330+-5 -> 46217 | D93: Both | E93: Medium | F93: 10-12 Months Before
A94: =FALSE() -> 0 | B94: Pay photographer deposit | C94: ='Get Started'!$C$4-330+-5 -> 46217 | D94: Both | E94: Medium | F94: 10-12 Months Before
A95: =FALSE() -> 0 | B95: Book videographer and sign contract | C95: ='Get Started'!$C$4-330+-5 -> 46217 | D95: Both | E95: Medium | F95: 10-12 Months Before
A96: =FALSE() -> 0 | B96: Pay videographer deposit | C96: ='Get Started'!$C$4-330+-5 -> 46217 | D96: Both | E96: Medium | F96: 10-12 Months Before
A97: =FALSE() -> 0 | B97: Book florist and sign contract | C97: ='Get Started'!$C$4-330+-5 -> 46217 | D97: Both | E97: Medium | F97: 10-12 Months Before
A98: =FALSE() -> 0 | B98: Book DJ or band and sign contract | C98: ='Get Started'!$C$4-330+-5 -> 46217 | D98: Both | E98: Medium | F98: 10-12 Months Before
A99: =FALSE() -> 0 | B99: Book officiant and confirm ceremony requirements | C99: ='Get Started'!$C$4-330+-5 -> 46217 | D99: Both | E99: Medium | F99: 10-12 Months Before
A100: =FALSE() -> 0 | B100: Start wedding dress shopping | C100: ='Get Started'!$C$4-330+-5 -> 46217 | D100: Both | E100: Medium | F100: 10-12 Months Before
A101: =FALSE() -> 0 | B101: Order the wedding dress | C101: ='Get Started'!$C$4-330+-5 -> 46217 | D101: Both | E101: Medium | F101: 10-12 Months Before
...

Sheet Wedding Itinerary
A1: WEDDING DAY ITINERARY
A3: Time | B3: Event | C3: Person in Charge | D3: Location
A4: 8:00 AM | B4: Bridal Party Get Ready | C4: Hair and Makeup Team | D4: Bridal Suite
A5: 9:30 AM | B5: Groom's Party Get Ready | C5: Groomsmen | D5: Groom's Suite
A6: 11:00 AM | B6: First Look | C6: Photographer | D6: Garden
A7: 11:30 AM | B7: Wedding Party Photos | C7: Photographer | D7: Garden
A8: 12:30 PM | B8: Family Formal Photos | C8: Photographer | D8: Garden
A9: 2:00 PM | B9: Guests Arrive | C9: Ushers | D9: Ceremony Site
A10: 2:30 PM | B10: Ceremony | C10: Officiant | D10: Ceremony Site
A11: 3:00 PM | B11: Cocktail Hour | C11: Catering Staff | D11: Terrace
A12: 4:00 PM | B12: Grand Entrance | C12: DJ or Band | D12: Reception Hall
A13: 4:15 PM | B13: First Dance | C13: DJ or Band | D13: Reception Hall
A14: 4:30 PM | B14: Welcome Toast | C14: Best Man | D14: Reception Hall
... A22: 10:45 PM | B22: Send Off | C22: Wedding Party | D22: Venue Exit

Sheet Wedding Activities
A1: WEDDING ACTIVITIES
A3: PLANNED ACTIVITIES
A4: Time Slot | B4: Location | C4: Person in Charge | D4: Activity Description
A5: 3:00 PM | B5: Terrace | C5: Wedding Planner | D5: Photo booth open for guests
A6: 3:15 PM | B6: Lawn | C6: Ushers | D6: Lawn games: cornhole and giant Jenga
A7: 4:30 PM | B7: Reception Hall | C7: DJ | D7: Guest book table with instant camera
A10: 50+ ACTIVITY IDEAS (REFERENCE LIST)
A11: - Photo booth with props | B11: - Fireworks display | C11: - Yard Yahtzee
A12: - Guest book alternative: fingerprint tree | B12: - Karaoke station | C12: - Photo booth with Polaroid guest book
A13: - Guest book alternative: polaroid wall | B13: - Slideshow of couple's photos | C13: - Wine or whiskey barrel signing ceremony
A14: - Lawn games: cornhole | B14: - Advice cards for the couple | C14: - Unity sand ceremony
A15: - Lawn games: giant Jenga | B15: - Wishing well card box | C15: - Handfasting ceremony
A16: - Lawn games: ring toss | B16: - Time capsule for guests to fill | C16: - Wine box time capsule ceremony
A17: - Lawn games: bocce ball | B17: - Coloring book table for kids | C17: - Live band cocktail hour set
A18: - Photo booth with instant camera | B18: - Kids' activity table with crafts | C18: - String quartet ceremony music
A19: - Custom cocktail bar | B19: - Photo scavenger hunt | C19: - Fire pit lounge area
A20: - Wine pull table | B20: - Trivia about the couple | C20: - Cigar and whiskey bar
A21: - S'mores bar | B21: - Custom playlist request cards | C21: - Popcorn bar
A22: - Late night snack station | B22: - Signature drink naming contest | C22: - Hot chocolate bar
... A28: - Photo booth with backdrop | B28: - Giant chess or checkers | C28: - Custom neon sign photo backdrop
A29: - Dance floor confetti drop | B29: - Bean bag toss
A30: - Sparkler send off | B30: - Ladder golf

Sheet Music Planner
A1: MUSIC PLANNER
A3: Share this tab with your DJ or band. Fill in artist, notes, and duration for each moment.
A5: CEREMONY
A6: Moment | B6: Artist | C6: Song / Version Notes | D6: Duration
A7: Prelude Music
A8: Processional
A9: Recessional
A11: COCKTAIL HOUR
A12: Moment | B12: Artist | C12: Song / Version Notes | D12: Duration
A13: Background Playlist
A15: RECEPTION ENTRANCE
A16: Moment | B16: Artist | C16: Song / Version Notes | D16: Duration
A17: Grand Entrance Song
A19: FIRST DANCE
A20: Moment | B20: Artist | C20: Song / Version Notes | D20: Duration
A21: First Dance Song
A23: PARENT DANCES
A24: Moment | B24: Artist | C24: Song / Version Notes | D24: Duration
A25: Father Daughter Dance
A26: Mother Son Dance
A28: PARTY AND DANCING
A29: Moment | B29: Artist | C29: Song / Version Notes | D29: Duration
A30: Open Dance Playlist
A31: Do Not Play List
A33: LAST SONG
A34: Moment | B34: Artist | C34: Song / Version Notes | D34: Duration
A35: Last Song of the Night

Sheet Packing List
A1: PACKING LIST
A3: BRIDE SUITE
A4: Item | B4: Packed | C4: Assigned To | D4: Notes
A5: Wedding dress | B5: =FALSE() -> FALSE | C5: Both
A6: Veil | B6: =FALSE() -> 0 | C6: Both
A7: Shoes | B7: =FALSE() -> 0 | C7: Both
A8: Undergarments | B8: =FALSE() -> 0 | C8: Both
A9: Jewelry | B9: =FALSE() -> 0 | C9: Both
A10: Something old, new, borrowed, blue | B10: =FALSE() -> 0 | C10: Both
A11: Emergency kit | B11: =FALSE() -> 0 | C11: Both
A12: Robe | B12: =FALSE() -> 0 | C12: Both
A14: GROOM SUITE
A15: Item | B15: Packed | C15: Assigned To | D15: Notes
A16: Suit or tuxedo | B16: =FALSE() -> FALSE | C16: Both
A17: Shoes | B17: =FALSE() -> 0 | C17: Both
A18: Tie or bow tie | B18: =FALSE() -> 0 | C18: Both
A19: Cufflinks | B19: =FALSE() -> 0 | C19: Both
A20: Belt | B20: =FALSE() -> 0 | C20: Both
A21: Socks | B21: =FALSE() -> 0 | C21: Both
A22: Watch | B22: =FALSE() -> 0 | C22: Both
A24: CEREMONY
A25: Item | B25: Packed | C25: Assigned To | D25: Notes
A26: Vows | B26: =FALSE() -> FALSE | C26: Both
A27: Rings | B27: =FALSE() -> 0 | C27: Both
A28: Marriage license | B28: =FALSE() -> 0 | C28: Both
A29: Unity ceremony items | B29: =FALSE() -> 0 | C29: Both
A30: Programs | B30: =FALSE() -> 0 | C30: Both
A32: RECEPTION
A33: Item | B33: Packed | C33: Assigned To | D33: Notes
A34: Guest book and pen | B34: =FALSE() -> FALSE | C34: Both
A35: Card box | B35: =FALSE() -> 0 | C35: Both
A36: Table numbers | B36: =FALSE() -> 0 | C36: Both
A37: Place cards | B37: =FALSE() -> 0 | C37: Both
A38: Cake serving set | B38: =FALSE() -> 0 | C38: Both
A39: Toasting flutes | B39: =FALSE() -> 0 | C39: Both
A41: EMERGENCY KIT
A42: Item | B42: Packed | C42: Assigned To | D42: Notes
A43: Safety pins | B43: =FALSE() -> FALSE | C43: Both
A44: Stain remover | B44: =FALSE() -> 0 | C44: Both
A45: Sewing kit | B45: =FALSE() -> 0 | C45: Both
A46: Bobby pins | B46: =FALSE() -> 0 | C46: Both
A47: Blister pads | B47: =FALSE() -> 0 | C47: Both
A48: Tissues | B48: =FALSE() -> 0 | C48: Both
A49: Mints | B49: =FALSE() -> 0 | C49: Both
A50: Pain reliever | B50: =FALSE() -> 0 | C50: Both
A51: Snacks | B51: =FALSE() -> 0 | C51: Both
A52: Phone charger | B52: =FALSE() -> 0 | C52: Both
A54: HONEYMOON
A55: Item | B55: Packed | C55: Assigned To | D55: Notes
A56: Passport | B56: =FALSE() -> FALSE | C56: Both
A57: Travel documents | B57: =FALSE() -> 0 | C57: Both
A58: Chargers | B58: =FALSE() -> 0 | C58: Both
A59: Toiletries | B59: =FALSE() -> 0 | C59: Both
A60: Outfits | B60: =FALSE() -> 0 | C60: Both
A61: Swimwear | B61: =FALSE() -> 0 | C61: Both
A62: Sunscreen | B62: =FALSE() -> 0 | C62: Both

Sheet Wedding Budget
A1: WEDDING BUDGET
A3: TOTAL BUDGET | C3: LEFT TO BUDGET | E3: TOTAL SPENT | G3: LEFT TO SPEND | I3: VENDOR PAYMENTS LEFT
A4: =B13 -> 21000 | C4: =B13-C32 -> 1400 | E4: =D32 -> 17900 | G4: =B13-D32 -> 3100 | I4: =SUMPRODUCT((A36:A75<>"")*(F36:F75<>"Paid")*D36:D75) -> 1600
A6: BUDGET FUNDING
A7: Contributor | B7: Amount
A8: Bride and Groom Savings | B8: 12000
A9: Bride's Parents | B9: 5000
A10: Groom's Parents | B10: 4000
A11: Other Family | B11: 0
A12: Other | B12: 0
A13: Total Budget | B13: =SUM(B8:B12) -> 21000
A15: EXPENSE SUMMARY
A16: Category | B16: Vendor / Subcategory | C16: Budget | D16: Actual | E16: Left
A17: Venue | B17: =IFERROR(INDEX('Vendor Selection'!$C$7:$C$96,MATCH(1,('Vendor Selection'!$B$7:$B$96=$A17)*('Vendor Selection'!$A$7:$A$96="Yes"),0)),"") -> Willow Creek Barn | C17: 6000 | D17: =IFERROR(SUMIFS('Vendor Selection'!$G$7:$G$96,'Vendor Selection'!$B$7:$B$96,$A17,'Vendor Selection'!$A$7:$A$96,"Yes"),0) -> 8500 | E17: =C17-D17 -> -2500
A18: Catering | B18: =IFERROR(INDEX('Vendor Selection'!$C$7:$C$96,MATCH(1,('Vendor Selection'!$B$7:$B$96=$A18)*('Vendor Selection'!$A$7:$A$96="Yes"),0)),"") -> Copper Table Catering | C18: 4200 | D18: =IFERROR(SUMIFS('Vendor Selection'!$G$7:$G$96,'Vendor Selection'!$B$7:$B$96,$A18,'Vendor Selection'!$A$7:$A$96,"Yes"),0) -> 6200 | E18: =C18-D18 -> -2000
A19: Photography | B19: =IFERROR(INDEX('Vendor Selection'!$C$7:$C$96,MATCH(1,('Vendor Selection'!$B$7:$B$96=$A19)*('Vendor Selection'!$A$7:$A$96="Yes"),0)),"") -> Golden Hour Studio | C19: 3200 | D19: =IFERROR(SUMIFS('Vendor Selection'!$G$7:$G$96,'Vendor Selection'!$B$7:$B$96,$A19,'Vendor Selection'!$A$7:$A$96,"Yes"),0) -> 3200 | E19: =C19-D19 -> 0
A20: Videography | B20: =IFERROR(INDEX('Vendor Selection'!$C$7:$C$96,MATCH(1,('Vendor Selection'!$B$7:$B$96=$A20)*('Vendor Selection'!$A$7:$A$96="Yes"),0)),"") | C20: 1500 | D20: =IFERROR(SUMIFS('Vendor Selection'!$G$7:$G$96,'Vendor Selection'!$B$7:$B$96,$A20,'Vendor Selection'!$A$7:$A$96,"Yes"),0) -> 0 | E20: =C20-D20 -> 1500
A21: Florist | B21: =IFERROR(INDEX('Vendor Selection'!$C$7:$C$96,MATCH(1,('Vendor Selection'!$B$7:$B$96=$A21)*('Vendor Selection'!$A$7:$A$96="Yes"),0)),"") | C21: 900 | D21: =IFERROR(SUMIFS('Vendor Selection'!$G$7:$G$96,'Vendor Selection'!$B$7:$B$96,$A21,'Vendor Selection'!$A$7:$A$96,"Yes"),0) -> 0 | E21: =C21-D21 -> 900
A22: DJ/Band | B22: =IFERROR(INDEX('Vendor Selection'!$C$7:$C$96,MATCH(1,('Vendor Selection'!$B$7:$B$96=$A22)*('Vendor Selection'!$A$7:$A$96="Yes"),0)),"") | C22: 800 | D22: =IFERROR(SUMIFS('Vendor Selection'!$G$7:$G$96,'Vendor Selection'!$B$7:$B$96,$A22,'Vendor Selection'!$A$7:$A$96,"Yes"),0) -> 0 | E22: =C22-D22 -> 800
A23: Officiant | B23: =IFERROR(INDEX('Vendor Selection'!$C$7:$C$96,MATCH(1,('Vendor Selection'!$B$7:$B$96=$A23)*('Vendor Selection'!$A$7:$A$96="Yes"),0)),"") | C23: 400 | D23: =IFERROR(SUMIFS('Vendor Selection'!$G$7:$G$96,'Vendor Selection'!$B$7:$B$96,$A23,'Vendor Selection'!$A$7:$A$96,"Yes"),0) -> 0 | E23: =C23-D23 -> 400
A24: Rentals | B24: =IFERROR(INDEX('Vendor Selection'!$C$7:$C$96,MATCH(1,('Vendor Selection'!$B$7:$B$96=$A24)*('Vendor Selection'!$A$7:$A$96="Yes"),0)),"") | C24: 500 | D24: =IFERROR(SUMIFS('Vendor Selection'!$G$7:$G$96,'Vendor Selection'!$B$7:$B$96,$A24,'Vendor Selection'!$A$7:$A$96,"Yes"),0) -> 0 | E24: =C24-D24 -> 500
A25: Decor | B25: =IFERROR(INDEX('Vendor Selection'!$C$7:$C$96,MATCH(1,('Vendor Selection'!$B$7:$B$96=$A25)*('Vendor Selection'!$A$7:$A$96="Yes"),0)),"") | C25: 400 | D25: =IFERROR(SUMIFS('Vendor Selection'!$G$7:$G$96,'Vendor Selection'!$B$7:$B$96,$A25,'Vendor Selection'!$A$7:$A$96,"Yes"),0) -> 0 | E25: =C25-D25 -> 400
A26: Hair & Makeup | B26: =IFERROR(INDEX('Vendor Selection'!$C$7:$C$96,MATCH(1,('Vendor Selection'!$B$7:$B$96=$A26)*('Vendor Selection'!$A$7:$A$96="Yes"),0)),"") | C26: 350 | D26: =IFERROR(SUMIFS('Vendor Selection'!$G$7:$G$96,'Vendor Selection'!$B$7:$B$96,$A26,'Vendor Selection'!$A$7:$A$96,"Yes"),0) -> 0 | E26: =C26-D26 -> 350
A27: Transportation | B27: =IFERROR(INDEX('Vendor Selection'!$C$7:$C$96,MATCH(1,('Vendor Selection'!$B$7:$B$96=$A27)*('Vendor Selection'!$A$7:$A$96="Yes"),0)),"") | C27: 250 | D27: =IFERROR(SUMIFS('Vendor Selection'!$G$7:$G$96,'Vendor Selection'!$B$7:$B$96,$A27,'Vendor Selection'!$A$7:$A$96,"Yes"),0) -> 0 | E27: =C27-D27 -> 250
A28: Cake | B28: =IFERROR(INDEX('Vendor Selection'!$C$7:$C$96,MATCH(1,('Vendor Selection'!$B$7:$B$96=$A28)*('Vendor Selection'!$A$7:$A$96="Yes"),0)),"") | C28: 350 | D28: =IFERROR(SUMIFS('Vendor Selection'!$G$7:$G$96,'Vendor Selection'!$B$7:$B$96,$A28,'Vendor Selection'!$A$7:$A$96,"Yes"),0) -> 0 | E28: =C28-D28 -> 350
... A31: Lighting | B31: =IFERROR(INDEX('Vendor Selection'!$C$7:$C$96,MATCH(1,('Vendor Selection'!$B$7:$B$96=$A31)*('Vendor Selection'!$A$7:$A$96="Yes"),0)),"") | C31: 250 | D31: =IFERROR(SUMIFS('Vendor Selection'!$G$7:$G$96,'Vendor Selection'!$B$7:$B$96,$A31,'Vendor Selection'!$A$7:$A$96,"Yes"),0) -> 0 | E31: =C31-D31 -> 250
A32: Total | C32: =SUM(C17:C31) -> 19600 | D32: =SUM(D17:D31) -> 17900 | E32: =SUM(E17:E31) -> 1700
A34: PAYMENT SCHEDULE AND LOG | I34: Reminder: payments turn red once past due and unpaid.
A35: Type | B35: Vendor Name | C35: Due Date | D35: Amount | E35: Paid Date | F35: Status | G35: Notes
A36: Deposit | B36: Willow Creek Barn | C36: ='Get Started'!$C$4+(-270) -> 46282 | D36: 4250 | E36: ='Get Started'!$C$4+(-260) -> 46292 | F36: =IF(E36<>"","Paid",IF(C36<TODAY(),"Overdue",IF(C36<=TODAY()+14,"Due Soon","Not Due"))) -> Paid
A37: Deposit | B37: Copper Table Catering | C37: ='Get Started'!$C$4+(-240) -> 46312 | D37: 3100 | E37: ='Get Started'!$C$4+(-230) -> 46322 | F37: =IF(E37<>"","Paid",IF(C37<TODAY(),"Overdue",IF(C37<=TODAY()+14,"Due Soon","Not Due"))) -> Paid
A38: Progress Payment | B38: Golden Hour Studio | C38: ='Get Started'!$C$4+(-120) -> 46432 | D38: 1600 | F38: =IF(E38<>"","Paid",IF(C38<TODAY(),"Overdue",IF(C38<=TODAY()+14,"Due Soon","Not Due"))) -> Not Due
F39: =IF(E39<>"","Paid",IF(AND(C39<>"",C39<TODAY()),"Overdue",IF(AND(C39<>"",C39<=TODAY()+14),"Due Soon",IF(C39<>"","Not Due",""))))
F40: =IF(E40<>"","Paid",IF(AND(C40<>"",C40<TODAY()),"Overdue",IF(AND(C40<>"",C40<=TODAY()+14),"Due Soon",IF(C40<>"","Not Due",""))))
F41: =IF(E41<>"","Paid",IF(AND(C41<>"",C41<TODAY()),"Overdue",IF(AND(C41<>"",C41<=TODAY()+14),"Due Soon",IF(C41<>"","Not Due",""))))
F42: =IF(E42<>"","Paid",IF(AND(C42<>"",C42<TODAY()),"Overdue",IF(AND(C42<>"",C42<=TODAY()+14),"Due Soon",IF(C42<>"","Not Due",""))))
F43: =IF(E43<>"","Paid",IF(AND(C43<>"",C43<TODAY()),"Overdue",IF(AND(C43<>"",C43<=TODAY()+14),"Due Soon",IF(C43<>"","Not Due",""))))
F44: =IF(E44<>"","Paid",IF(AND(C44<>"",C44<TODAY()),"Overdue",IF(AND(C44<>"",C44<=TODAY()+14),"Due Soon",IF(C44<>"","Not Due",""))))
F45: =IF(E45<>"","Paid",IF(AND(C45<>"",C45<TODAY()),"Overdue",IF(AND(C45<>"",C45<=TODAY()+14),"Due Soon",IF(C45<>"","Not Due",""))))
F46: =IF(E46<>"","Paid",IF(AND(C46<>"",C46<TODAY()),"Overdue",IF(AND(C46<>"",C46<=TODAY()+14),"Due Soon",IF(C46<>"","Not Due",""))))
F47: =IF(E47<>"","Paid",IF(AND(C47<>"",C47<TODAY()),"Overdue",IF(AND(C47<>"",C47<=TODAY()+14),"Due Soon",IF(C47<>"","Not Due",""))))
F48: =IF(E48<>"","Paid",IF(AND(C48<>"",C48<TODAY()),"Overdue",IF(AND(C48<>"",C48<=TODAY()+14),"Due Soon",IF(C48<>"","Not Due",""))))
F49: =IF(E49<>"","Paid",IF(AND(C49<>"",C49<TODAY()),"Overdue",IF(AND(C49<>"",C49<=TODAY()+14),"Due Soon",IF(C49<>"","Not Due",""))))
F50: =IF(E50<>"","Paid",IF(AND(C50<>"",C50<TODAY()),"Overdue",IF(AND(C50<>"",C50<=TODAY()+14),"Due Soon",IF(C50<>"","Not Due",""))))
... F75: =IF(E75<>"","Paid",IF(AND(C75<>"",C75<TODAY()),"Overdue",IF(AND(C75<>"",C75<=TODAY()+14),"Due Soon",IF(C75<>"","Not Due",""))))

Sheet Vendor Selection
A1: VENDOR SELECTION AND RESEARCH
A3: SELECTION PROGRESS | C3: TOTAL COST | E3: VENDORS FINALIZED | L3: Category | M3: Cost
A4: =COUNTIFS(A7:A96,"Yes")/COUNTIF(B7:B96,"<>") -> 0.6 | C4: =SUMIFS(G7:G96,A7:A96,"Yes") -> 17900 | E4: =COUNTIFS(A7:A96,"Yes") -> 3 | L4: Venue | M4: =SUMIFS($G$7:$G$96,$B$7:$B$96,L4,$A$7:$A$96,"Yes") -> 8500
L5: Catering | M5: =SUMIFS($G$7:$G$96,$B$7:$B$96,L5,$A$7:$A$96,"Yes") -> 6200
A6: Final | B6: Category | C6: Name | D6: Contact | E6: Email | F6: Package | G6: Amount | H6: Availability | I6: Rating (1-5) | J6: Notes | L6: Photography | M6: =SUMIFS($G$7:$G$96,$B$7:$B$96,L6,$A$7:$A$96,"Yes") -> 3200
A7: Yes | B7: Venue | C7: Willow Creek Barn | D7: 555-0101 | E7: info@willowcreekbarn.com | F7: Full Day Rental | G7: 8500 | H7: Confirmed | I7: 5 | J7: Holds 200 guests, includes tables and chairs | L7: Videography | M7: =SUMIFS($G$7:$G$96,$B$7:$B$96,L7,$A$7:$A$96,"Yes") -> 0
A8: Yes | B8: Catering | C8: Copper Table Catering | D8: 555-0102 | E8: hello@coppertable.com | F8: Plated Dinner, 3 Course | G8: 6200 | H8: Confirmed | I8: 5 | J8: Tasting scheduled, great reviews | L8: Florist | M8: =SUMIFS($G$7:$G$96,$B$7:$B$96,L8,$A$7:$A$96,"Yes") -> 0
A9: Yes | B9: Photography | C9: Golden Hour Studio | D9: 555-0103 | E9: book@goldenhourstudio.com | F9: 8 Hour Coverage | G9: 3200 | H9: Confirmed | I9: 5 | J9: Second shooter included | L9: DJ/Band | M9: =SUMIFS($G$7:$G$96,$B$7:$B$96,L9,$A$7:$A$96,"Yes") -> 0
A10: No | B10: Videography | C10: Storyframe Films | D10: 555-0104 | E10: team@storyframefilms.com | F10: Highlight Reel | G10: 2400 | H10: Pending | I10: 4 | J10: Waiting on final quote | L10: Officiant | M10: =SUMIFS($G$7:$G$96,$B$7:$B$96,L10,$A$7:$A$96,"Yes") -> 0
A11: No | B11: Florist | C11: Petal and Vine | D11: 555-0105 | E11: orders@petalandvine.com | F11: Full Florals Package | G11: 2100 | H11: Pending | I11: 4 | L11: Rentals | M11: =SUMIFS($G$7:$G$96,$B$7:$B$96,L11,$A$7:$A$96,"Yes") -> 0
A12: No | L12: Decor | M12: =SUMIFS($G$7:$G$96,$B$7:$B$96,L12,$A$7:$A$96,"Yes") -> 0
A13: No | L13: Hair & Makeup | M13: =SUMIFS($G$7:$G$96,$B$7:$B$96,L13,$A$7:$A$96,"Yes") -> 0
A14: No | L14: Transportation | M14: =SUMIFS($G$7:$G$96,$B$7:$B$96,L14,$A$7:$A$96,"Yes") -> 0
A15: No | L15: Cake | M15: =SUMIFS($G$7:$G$96,$B$7:$B$96,L15,$A$7:$A$96,"Yes") -> 0
A16: No | L16: Stationery | M16: =SUMIFS($G$7:$G$96,$B$7:$B$96,L16,$A$7:$A$96,"Yes") -> 0
A17: No | L17: Favors | M17: =SUMIFS($G$7:$G$96,$B$7:$B$96,L17,$A$7:$A$96,"Yes") -> 0
A18: No | L18: Lighting | M18: =SUMIFS($G$7:$G$96,$B$7:$B$96,L18,$A$7:$A$96,"Yes") -> 0
A19: No
A20: No
A21: No
A22: No
A23: No
A24: No
A25: No
A26: No
A27: No
A28: No
A29: No
A30: No
... A96: No

Sheet Venue Comparison
A1: VENUE COMPARISON
A3: Field | B3: Venue 1 | C3: Venue 2 | D3: Venue 3 | E3: Venue 4 | F3: Venue 5
A4: Name
A5: Photo Placeholder | B5: [ photo ] | C5: [ photo ] | D5: [ photo ] | E5: [ photo ] | F5: [ photo ]
A6: Contact Info
A7: Capacity
A8: Availability
A9: Venue Fee
A10: Ceremony Fee
A11: Reception Fee
A12: Setup Fee
A13: Cleanup Fee
A14: Service Charge
A15: Food and Drinks
A16: Alcohol
A17: Cake Cutting Fee
A18: Total | B18: =B9+B10+B11+B12+B13+B14+B15+B16+B17 -> 0 | C18: =C9+C10+C11+C12+C13+C14+C15+C16+C17 -> 0 | D18: =D9+D10+D11+D12+D13+D14+D15+D16+D17 -> 0 | E18: =E9+E10+E11+E12+E13+E14+E15+E16+E17 -> 0 | F18: =F9+F10+F11+F12+F13+F14+F15+F16+F17 -> 0
A19: Winner | B19: =IF(AND(B18<>0,B18=MIN(B18,C18,D18,E18,F18)),"Best Value","") | C19: =IF(AND(C18<>0,C18=MIN(B18,C18,D18,E18,F18)),"Best Value","") | D19: =IF(AND(D18<>0,D18=MIN(B18,C18,D18,E18,F18)),"Best Value","") | E19: =IF(AND(E18<>0,E18=MIN(B18,C18,D18,E18,F18)),"Best Value","") | F19: =IF(AND(F18<>0,F18=MIN(B18,C18,D18,E18,F18)),"Best Value","")

Sheet Food and Drinks
A1: FOOD AND DRINKS
A3: REHEARSAL DINNER
A4: APPETIZERS | I4: Event | J4: Total Cost
A5: Final | B5: Item | C5: Tasting Rating | D5: Amount | E5: Qty | F5: Total | I5: Rehearsal Dinner | J5: =B32 -> 0
A6: =FALSE() -> 0 | D6: 0 | E6: 1 | F6: =D6*E6 -> 0 | I6: Reception | J6: =B64 -> 0
A7: =FALSE() -> 0 | D7: 0 | E7: 1 | F7: =D7*E7 -> 0
A8: =FALSE() -> 0 | D8: 0 | E8: 1 | F8: =D8*E8 -> 0
A9: =FALSE() -> 0 | D9: 0 | E9: 1 | F9: =D9*E9 -> 0
A11: MAIN COURSE
A12: Final | B12: Item | C12: Tasting Rating | D12: Amount | E12: Qty | F12: Total
A13: =FALSE() -> 0 | D13: 0 | E13: 1 | F13: =D13*E13 -> 0
A14: =FALSE() -> 0 | D14: 0 | E14: 1 | F14: =D14*E14 -> 0
A15: =FALSE() -> 0 | D15: 0 | E15: 1 | F15: =D15*E15 -> 0
A16: =FALSE() -> 0 | D16: 0 | E16: 1 | F16: =D16*E16 -> 0
A18: DESSERTS
A19: Final | B19: Item | C19: Tasting Rating | D19: Amount | E19: Qty | F19: Total
A20: =FALSE() -> 0 | D20: 0 | E20: 1 | F20: =D20*E20 -> 0
A21: =FALSE() -> 0 | D21: 0 | E21: 1 | F21: =D21*E21 -> 0
A22: =FALSE() -> 0 | D22: 0 | E22: 1 | F22: =D22*E22 -> 0
A23: =FALSE() -> 0 | D23: 0 | E23: 1 | F23: =D23*E23 -> 0
A25: DRINKS
A26: Final | B26: Item | C26: Tasting Rating | D26: Amount | E26: Qty | F26: Total
A27: =FALSE() -> 0 | D27: 0 | E27: 1 | F27: =D27*E27 -> 0
A28: =FALSE() -> 0 | D28: 0 | E28: 1 | F28: =D28*E28 -> 0
A29: =FALSE() -> 0 | D29: 0 | E29: 1 | F29: =D29*E29 -> 0
A30: =FALSE() -> 0 | D30: 0 | E30: 1 | F30: =D30*E30 -> 0
A32: Rehearsal Dinner Total Cost | B32: =SUM(F6:F9)+SUM(F13:F16)+SUM(F20:F23)+SUM(F27:F30) -> 0
A35: RECEPTION
A36: APPETIZERS
A37: Final | B37: Item | C37: Tasting Rating | D37: Amount | E37: Qty | F37: Total
A38: =FALSE() -> 0 | D38: 0 | E38: 1 | F38: =D38*E38 -> 0
A39: =FALSE() -> 0 | D39: 0 | E39: 1 | F39: =D39*E39 -> 0
A40: =FALSE() -> 0 | D40: 0 | E40: 1 | F40: =D40*E40 -> 0
A41: =FALSE() -> 0 | D41: 0 | E41: 1 | F41: =D41*E41 -> 0
A43: MAIN COURSE
A44: Final | B44: Item | C44: Tasting Rating | D44: Amount | E44: Qty | F44: Total
A45: =FALSE() -> 0 | D45: 0 | E45: 1 | F45: =D45*E45 -> 0
A46: =FALSE() -> 0 | D46: 0 | E46: 1 | F46: =D46*E46 -> 0
A47: =FALSE() -> 0 | D47: 0 | E47: 1 | F47: =D47*E47 -> 0
A48: =FALSE() -> 0 | D48: 0 | E48: 1 | F48: =D48*E48 -> 0
A50: DESSERTS
A51: Final | B51: Item | C51: Tasting Rating | D51: Amount | E51: Qty | F51: Total
A52: =FALSE() -> 0 | D52: 0 | E52: 1 | F52: =D52*E52 -> 0
A53: =FALSE() -> 0 | D53: 0 | E53: 1 | F53: =D53*E53 -> 0
A54: =FALSE() -> 0 | D54: 0 | E54: 1 | F54: =D54*E54 -> 0
A55: =FALSE() -> 0 | D55: 0 | E55: 1 | F55: =D55*E55 -> 0
A57: DRINKS
A58: Final | B58: Item | C58: Tasting Rating | D58: Amount | E58: Qty | F58: Total
A59: =FALSE() -> 0 | D59: 0 | E59: 1 | F59: =D59*E59 -> 0
A60: =FALSE() -> 0 | D60: 0 | E60: 1 | F60: =D60*E60 -> 0
A61: =FALSE() -> 0 | D61: 0 | E61: 1 | F61: =D61*E61 -> 0
A62: =FALSE() -> 0 | D62: 0 | E62: 1 | F62: =D62*E62 -> 0
A64: Reception Total Cost | B64: =SUM(F38:F41)+SUM(F45:F48)+SUM(F52:F55)+SUM(F59:F62) -> 0

Sheet Photo and Video Shot List
A1: PHOTO AND VIDEO SHOT LIST
A3: PHOTOGRAPHY
A4: GETTING READY
A5: Captured | B5: Shot | C5: Notes
A6: =FALSE() -> 0 | B6: Dress on hanger
A7: =FALSE() -> 0 | B7: Rings close up
A8: =FALSE() -> 0 | B8: Invitation suite flat lay
A9: =FALSE() -> 0 | B9: Bride getting into dress
A10: =FALSE() -> 0 | B10: Groom getting dressed
A11: =FALSE() -> 0 | B11: Bridesmaids helping bride
A12: =FALSE() -> 0 | B12: Groomsmen candid moments
A13: =FALSE() -> 0 | B13: First look with parent
A15: CEREMONY
A16: Captured | B16: Shot | C16: Notes
A17: =FALSE() -> 0 | B17: Ceremony site before guests arrive
A18: =FALSE() -> 0 | B18: Guests arriving
A19: =FALSE() -> 0 | B19: Processional
A20: =FALSE() -> 0 | B20: Bride's entrance
A21: =FALSE() -> 0 | B21: Vows exchange
A22: =FALSE() -> 0 | B22: Ring exchange
A23: =FALSE() -> 0 | B23: First kiss
A24: =FALSE() -> 0 | B24: Recessional
A26: FAMILY FORMALS
A27: Captured | B27: Shot | C27: Notes
A28: =FALSE() -> 0 | B28: Immediate family with couple
A29: =FALSE() -> 0 | B29: Extended family with couple
A30: =FALSE() -> 0 | B30: Bridal party with couple
A31: =FALSE() -> 0 | B31: Bride with her parents
A32: =FALSE() -> 0 | B32: Groom with his parents
A33: =FALSE() -> 0 | B33: Grandparents with couple
A35: RECEPTION
A36: Captured | B36: Shot | C36: Notes
A37: =FALSE() -> 0 | B37: Reception decor detail shots
A38: =FALSE() -> 0 | B38: Grand entrance
A39: =FALSE() -> 0 | B39: First dance
A40: =FALSE() -> 0 | B40: Parent dances
A41: =FALSE() -> 0 | B41: Toasts and speeches
A42: =FALSE() -> 0 | B42: Cake cutting
A43: =FALSE() -> 0 | B43: Bouquet toss
A44: =FALSE() -> 0 | B44: Garter toss
A45: =FALSE() -> 0 | B45: Open dancing
A46: =FALSE() -> 0 | B46: Send off
A48: DETAILS
A49: Captured | B49: Shot | C49: Notes
A50: =FALSE() -> 0 | B50: Rings
A51: =FALSE() -> 0 | B51: Bouquet
A52: =FALSE() -> 0 | B52: Shoes
A53: =FALSE() -> 0 | B53: Invitation suite
A54: =FALSE() -> 0 | B54: Centerpieces
A55: =FALSE() -> 0 | B55: Cake
A56: =FALSE() -> 0 | B56: Favors
A57: =FALSE() -> 0 | B57: Signage
A59: VIDEOGRAPHY
A60: GETTING READY
A61: Captured | B61: Shot | C61: Notes
A62: =FALSE() -> 0 | B62: Dress on hanger
A63: =FALSE() -> 0 | B63: Rings close up
A64: =FALSE() -> 0 | B64: Invitation suite flat lay
A65: =FALSE() -> 0 | B65: Bride getting into dress
A66: =FALSE() -> 0 | B66: Groom getting dressed
A67: =FALSE() -> 0 | B67: Bridesmaids helping bride
A68: =FALSE() -> 0 | B68: Groomsmen candid moments
A69: =FALSE() -> 0 | B69: First look with parent
A71: CEREMONY
A72: Captured | B72: Shot | C72: Notes
A73: =FALSE() -> 0 | B73: Ceremony site before guests arrive
A74: =FALSE() -> 0 | B74: Guests arriving
A75: =FALSE() -> 0 | B75: Processional
A76: =FALSE() -> 0 | B76: Bride's entrance
A77: =FALSE() -> 0 | B77: Vows exchange
A78: =FALSE() -> 0 | B78: Ring exchange
A79: =FALSE() -> 0 | B79: First kiss
A80: =FALSE() -> 0 | B80: Recessional
A82: FAMILY FORMALS
A83: Captured | B83: Shot | C83: Notes
A84: =FALSE() -> 0 | B84: Immediate family with couple
A85: =FALSE() -> 0 | B85: Extended family with couple
A86: =FALSE() -> 0 | B86: Bridal party with couple
A87: =FALSE() -> 0 | B87: Bride with her parents
A88: =FALSE() -> 0 | B88: Groom with his parents
A89: =FALSE() -> 0 | B89: Grandparents with couple
A91: RECEPTION
A92: Captured | B92: Shot | C92: Notes
A93: =FALSE() -> 0 | B93: Reception decor detail shots
A94: =FALSE() -> 0 | B94: Grand entrance
A95: =FALSE() -> 0 | B95: First dance
A96: =FALSE() -> 0 | B96: Parent dances
A97: =FALSE() -> 0 | B97: Toasts and speeches
A98: =FALSE() -> 0 | B98: Cake cutting
A99: =FALSE() -> 0 | B99: Bouquet toss
A100: =FALSE() -> 0 | B100: Garter toss
A101: =FALSE() -> 0 | B101: Open dancing
A102: =FALSE() -> 0 | B102: Send off
A104: DETAILS
A105: Captured | B105: Shot | C105: Notes
A106: =FALSE() -> 0 | B106: Rings
A107: =FALSE() -> 0 | B107: Bouquet
A108: =FALSE() -> 0 | B108: Shoes
A109: =FALSE() -> 0 | B109: Invitation suite
A110: =FALSE() -> 0 | B110: Centerpieces
...

Sheet Guest List
A1: GUEST LIST
A3: TOTAL GUESTS | C3: SAVE THE DATE SENT | E3: INVITATION SENT | G3: CONFIRMED | I3: RSVP DEADLINE | K3: DAYS LEFT TO RSVP | N3: Guest Of | O3: Count
A4: =COUNTA(A7:A206) -> 6 | C4: =COUNTIFS(D7:D206,TRUE()) -> 6 | E4: =COUNTIFS(E7:E206,TRUE()) -> 6 | G4: =COUNTIFS(F7:F206,"Yes") -> 2 | I4: ='Get Started'!$C$4-30 -> 46522 | K4: =I4-TODAY() -> 270 | N4: Bride | O4: =COUNTIFS($B$7:$B$206,N4) -> 2
N5: Groom | O5: =COUNTIFS($B$7:$B$206,N5) -> 2
A6: Name | B6: Guest Tag | C6: Child | D6: Save the Date | E6: Invitation | F6: RSVP | G6: Meal Preference | H6: Rehearsal Dinner | I6: Contact | J6: Email | K6: Address | N6: Both | O6: =COUNTIFS($B$7:$B$206,N6) -> 2
A7: Alex Johnson | B7: Bride | C7: =FALSE() -> 0 | D7: =TRUE() -> 1 | E7: =TRUE() -> 1 | F7: Yes | G7: Chicken | H7: =FALSE() -> 0
A8: Sam Rivera | B8: Groom | C8: =FALSE() -> 0 | D8: =TRUE() -> 1 | E8: =TRUE() -> 1 | F8: No | G8: Beef | H8: =FALSE() -> 0 | N8: Guest Type | O8: Count
A9: Jamie Lee | B9: Both | C9: =FALSE() -> 0 | D9: =TRUE() -> 1 | E9: =TRUE() -> 1 | F9: Awaited | G9: Fish | H9: =FALSE() -> 0 | N9: Chicken | O9: =COUNTIFS($G$7:$G$206,N9) -> 1
A10: Morgan Kim | B10: Bride | C10: =FALSE() -> 0 | D10: =TRUE() -> 1 | E10: =TRUE() -> 1 | F10: Yes | G10: Vegetarian | H10: =FALSE() -> 0 | N10: Beef | O10: =COUNTIFS($G$7:$G$206,N10) -> 1
A11: Taylor Brooks | B11: Groom | C11: =FALSE() -> 0 | D11: =TRUE() -> 1 | E11: =TRUE() -> 1 | F11: No | G11: Vegan | H11: =FALSE() -> 0 | N11: Fish | O11: =COUNTIFS($G$7:$G$206,N11) -> 1
A12: Casey Adams | B12: Both | C12: =FALSE() -> 0 | D12: =TRUE() -> 1 | E12: =TRUE() -> 1 | F12: Awaited | G12: Kids Meal | H12: =FALSE() -> 0 | N12: Vegetarian | O12: =COUNTIFS($G$7:$G$206,N12) -> 1
C13: =FALSE() -> 0 | D13: =FALSE() -> 0 | E13: =FALSE() -> 0 | H13: =FALSE() -> 0 | N13: Vegan | O13: =COUNTIFS($G$7:$G$206,N13) -> 1
C14: =FALSE() -> 0 | D14: =FALSE() -> 0 | E14: =FALSE() -> 0 | H14: =FALSE() -> 0 | N14: Kids Meal | O14: =COUNTIFS($G$7:$G$206,N14) -> 1
C15: =FALSE() -> 0 | D15: =FALSE() -> 0 | E15: =FALSE() -> 0 | H15: =FALSE() -> 0 | N15: No Preference | O15: =COUNTIFS($G$7:$G$206,N15) -> 0
C16: =FALSE() -> 0 | D16: =FALSE() -> 0 | E16: =FALSE() -> 0 | H16: =FALSE() -> 0
C17: =FALSE() -> 0 | D17: =FALSE() -> 0 | E17: =FALSE() -> 0 | H17: =FALSE() -> 0
C18: =FALSE() -> 0 | D18: =FALSE() -> 0 | E18: =FALSE() -> 0 | H18: =FALSE() -> 0
C19: =FALSE() -> 0 | D19: =FALSE() -> 0 | E19: =FALSE() -> 0 | H19: =FALSE() -> 0
C20: =FALSE() -> 0 | D20: =FALSE() -> 0 | E20: =FALSE() -> 0 | H20: =FALSE() -> 0
C21: =FALSE() -> 0 | D21: =FALSE() -> 0 | E21: =FALSE() -> 0 | H21: =FALSE() -> 0
C22: =FALSE() -> 0 | D22: =FALSE() -> 0 | E22: =FALSE() -> 0 | H22: =FALSE() -> 0
C23: =FALSE() -> 0 | D23: =FALSE() -> 0 | E23: =FALSE() -> 0 | H23: =FALSE() -> 0
C24: =FALSE() -> 0 | D24: =FALSE() -> 0 | E24: =FALSE() -> 0 | H24: =FALSE() -> 0
C25: =FALSE() -> 0 | D25: =FALSE() -> 0 | E25: =FALSE() -> 0 | H25: =FALSE() -> 0
C26: =FALSE() -> 0 | D26: =FALSE() -> 0 | E26: =FALSE() -> 0 | H26: =FALSE() -> 0
C27: =FALSE() -> 0 | D27: =FALSE() -> 0 | E27: =FALSE() -> 0 | H27: =FALSE() -> 0
... C206: =FALSE() -> 0 | D206: =FALSE() -> 0 | E206: =FALSE() -> 0 | H206: =FALSE() -> 0

Sheet Reception Seating Plan
A1: RECEPTION SEATING PLAN
A3: TOTAL SEATS | C3: CONFIRMED GUESTS | E3: CONFIRMED SEATS | G3: TENTATIVE SEATS | I3: REMAINING SEATS | K3: CONFIRMED TO BE SEATED
A4: =10*8 -> 80 | C4: =COUNTIFS('Guest List'!$F$7:$F$206,"Yes") -> 2 | E4: =COUNTIFS(D10:D29,"<>") -> 0 | G4: =COUNTIFS('Guest List'!$F$7:$F$206,"Awaited") -> 2 | I4: =A4-E4 -> 80 | K4: =IFERROR(E4/C4,0) -> 0
A6: Filter reference: Guest Tag / RSVP status are pulled live from the Guest List tab below.
A8: GUESTS WITHOUT A SEAT
A9: Name | B9: Guest Tag | C9: RSVP | D9: Table #
A10: =IF('Guest List'!$F7="Yes",'Guest List'!$A7,"") -> Alex Johnson | B10: =IF(A10<>"",'Guest List'!$B7,"") -> Bride | C10: =IF(A10<>"",'Guest List'!$F7,"") -> Yes
A11: =IF('Guest List'!$F8="Yes",'Guest List'!$A8,"") | B11: =IF(A11<>"",'Guest List'!$B8,"") | C11: =IF(A11<>"",'Guest List'!$F8,"")
A12: =IF('Guest List'!$F9="Yes",'Guest List'!$A9,"") | B12: =IF(A12<>"",'Guest List'!$B9,"") | C12: =IF(A12<>"",'Guest List'!$F9,"")
A13: =IF('Guest List'!$F10="Yes",'Guest List'!$A10,"") -> Morgan Kim | B13: =IF(A13<>"",'Guest List'!$B10,"") -> Bride | C13: =IF(A13<>"",'Guest List'!$F10,"") -> Yes
A14: =IF('Guest List'!$F11="Yes",'Guest List'!$A11,"") | B14: =IF(A14<>"",'Guest List'!$B11,"") | C14: =IF(A14<>"",'Guest List'!$F11,"")
A15: =IF('Guest List'!$F12="Yes",'Guest List'!$A12,"") | B15: =IF(A15<>"",'Guest List'!$B12,"") | C15: =IF(A15<>"",'Guest List'!$F12,"")
A16: =IF('Guest List'!$F13="Yes",'Guest List'!$A13,"") | B16: =IF(A16<>"",'Guest List'!$B13,"") | C16: =IF(A16<>"",'Guest List'!$F13,"")
A17: =IF('Guest List'!$F14="Yes",'Guest List'!$A14,"") | B17: =IF(A17<>"",'Guest List'!$B14,"") | C17: =IF(A17<>"",'Guest List'!$F14,"")
A18: =IF('Guest List'!$F15="Yes",'Guest List'!$A15,"") | B18: =IF(A18<>"",'Guest List'!$B15,"") | C18: =IF(A18<>"",'Guest List'!$F15,"")
A19: =IF('Guest List'!$F16="Yes",'Guest List'!$A16,"") | B19: =IF(A19<>"",'Guest List'!$B16,"") | C19: =IF(A19<>"",'Guest List'!$F16,"")
A20: =IF('Guest List'!$F17="Yes",'Guest List'!$A17,"") | B20: =IF(A20<>"",'Guest List'!$B17,"") | C20: =IF(A20<>"",'Guest List'!$F17,"")
A21: =IF('Guest List'!$F18="Yes",'Guest List'!$A18,"") | B21: =IF(A21<>"",'Guest List'!$B18,"") | C21: =IF(A21<>"",'Guest List'!$F18,"")
... A29: =IF('Guest List'!$F26="Yes",'Guest List'!$A26,"") | B29: =IF(A29<>"",'Guest List'!$B26,"") | C29: =IF(A29<>"",'Guest List'!$F26,"")
A31: TABLE BLOCKS
A32: Table 1 | G32: Table 2
A33: Capacity | B33: 8 | C33: Confirmed Seats | D33: =COUNTIFS(A36:A43,"<>") -> 0 | G33: Capacity | H33: 8 | I33: Confirmed Seats | J33: =COUNTIFS(A36:A43,"<>") -> 0
A34: Guest Tags Included | B34: =_xlfn.TEXTJOIN(", ",TRUE(),IF(COUNTIF(B36:B43,"Bride")>0,"Bride",""),IF(COUNTIF(B36:B43,"Groom")>0,"Groom",""),IF(COUNTIF(B36:B43,"Both")>0,"Both","")) | G34: Guest Tags Included | H34: =_xlfn.TEXTJOIN(", ",TRUE(),IF(COUNTIF(B36:B43,"Bride")>0,"Bride",""),IF(COUNTIF(B36:B43,"Groom")>0,"Groom",""),IF(COUNTIF(B36:B43,"Both")>0,"Both",""))
A35: Name | B35: Guest Tag | C35: # | G35: Name | H35: Guest Tag | I35: #
B36: =IFERROR(INDEX('Guest List'!$B$7:$B$206,MATCH(A36,'Guest List'!$A$7:$A$206,0)),"") | C36: 1 | H36: =IFERROR(INDEX('Guest List'!$B$7:$B$206,MATCH(G36,'Guest List'!$A$7:$A$206,0)),"") | I36: 1
B37: =IFERROR(INDEX('Guest List'!$B$7:$B$206,MATCH(A37,'Guest List'!$A$7:$A$206,0)),"") | C37: 2 | H37: =IFERROR(INDEX('Guest List'!$B$7:$B$206,MATCH(G37,'Guest List'!$A$7:$A$206,0)),"") | I37: 2
B38: =IFERROR(INDEX('Guest List'!$B$7:$B$206,MATCH(A38,'Guest List'!$A$7:$A$206,0)),"") | C38: 3 | H38: =IFERROR(INDEX('Guest List'!$B$7:$B$206,MATCH(G38,'Guest List'!$A$7:$A$206,0)),"") | I38: 3
B39: =IFERROR(INDEX('Guest List'!$B$7:$B$206,MATCH(A39,'Guest List'!$A$7:$A$206,0)),"") | C39: 4 | H39: =IFERROR(INDEX('Guest List'!$B$7:$B$206,MATCH(G39,'Guest List'!$A$7:$A$206,0)),"") | I39: 4
B40: =IFERROR(INDEX('Guest List'!$B$7:$B$206,MATCH(A40,'Guest List'!$A$7:$A$206,0)),"") | C40: 5 | H40: =IFERROR(INDEX('Guest List'!$B$7:$B$206,MATCH(G40,'Guest List'!$A$7:$A$206,0)),"") | I40: 5
B41: =IFERROR(INDEX('Guest List'!$B$7:$B$206,MATCH(A41,'Guest List'!$A$7:$A$206,0)),"") | C41: 6 | H41: =IFERROR(INDEX('Guest List'!$B$7:$B$206,MATCH(G41,'Guest List'!$A$7:$A$206,0)),"") | I41: 6
B42: =IFERROR(INDEX('Guest List'!$B$7:$B$206,MATCH(A42,'Guest List'!$A$7:$A$206,0)),"") | C42: 7 | H42: =IFERROR(INDEX('Guest List'!$B$7:$B$206,MATCH(G42,'Guest List'!$A$7:$A$206,0)),"") | I42: 7
B43: =IFERROR(INDEX('Guest List'!$B$7:$B$206,MATCH(A43,'Guest List'!$A$7:$A$206,0)),"") | C43: 8 | H43: =IFERROR(INDEX('Guest List'!$B$7:$B$206,MATCH(G43,'Guest List'!$A$7:$A$206,0)),"") | I43: 8
A49: Table 3 | G49: Table 4
A50: Capacity | B50: 8 | C50: Confirmed Seats | D50: =COUNTIFS(A53:A60,"<>") -> 0 | G50: Capacity | H50: 8 | I50: Confirmed Seats | J50: =COUNTIFS(A53:A60,"<>") -> 0
A51: Guest Tags Included | B51: =_xlfn.TEXTJOIN(", ",TRUE(),IF(COUNTIF(B53:B60,"Bride")>0,"Bride",""),IF(COUNTIF(B53:B60,"Groom")>0,"Groom",""),IF(COUNTIF(B53:B60,"Both")>0,"Both","")) | G51: Guest Tags Included | H51: =_xlfn.TEXTJOIN(", ",TRUE(),IF(COUNTIF(B53:B60,"Bride")>0,"Bride",""),IF(COUNTIF(B53:B60,"Groom")>0,"Groom",""),IF(COUNTIF(B53:B60,"Both")>0,"Both",""))
A52: Name | B52: Guest Tag | C52: # | G52: Name | H52: Guest Tag | I52: #
B53: =IFERROR(INDEX('Guest List'!$B$7:$B$206,MATCH(A53,'Guest List'!$A$7:$A$206,0)),"") | C53: 1 | H53: =IFERROR(INDEX('Guest List'!$B$7:$B$206,MATCH(G53,'Guest List'!$A$7:$A$206,0)),"") | I53: 1
B54: =IFERROR(INDEX('Guest List'!$B$7:$B$206,MATCH(A54,'Guest List'!$A$7:$A$206,0)),"") | C54: 2 | H54: =IFERROR(INDEX('Guest List'!$B$7:$B$206,MATCH(G54,'Guest List'!$A$7:$A$206,0)),"") | I54: 2
B55: =IFERROR(INDEX('Guest List'!$B$7:$B$206,MATCH(A55,'Guest List'!$A$7:$A$206,0)),"") | C55: 3 | H55: =IFERROR(INDEX('Guest List'!$B$7:$B$206,MATCH(G55,'Guest List'!$A$7:$A$206,0)),"") | I55: 3
B56: =IFERROR(INDEX('Guest List'!$B$7:$B$206,MATCH(A56,'Guest List'!$A$7:$A$206,0)),"") | C56: 4 | H56: =IFERROR(INDEX('Guest List'!$B$7:$B$206,MATCH(G56,'Guest List'!$A$7:$A$206,0)),"") | I56: 4
B57: =IFERROR(INDEX('Guest List'!$B$7:$B$206,MATCH(A57,'Guest List'!$A$7:$A$206,0)),"") | C57: 5 | H57: =IFERROR(INDEX('Guest List'!$B$7:$B$206,MATCH(G57,'Guest List'!$A$7:$A$206,0)),"") | I57: 5
B58: =IFERROR(INDEX('Guest List'!$B$7:$B$206,MATCH(A58,'Guest List'!$A$7:$A$206,0)),"") | C58: 6 | H58: =IFERROR(INDEX('Guest List'!$B$7:$B$206,MATCH(G58,'Guest List'!$A$7:$A$206,0)),"") | I58: 6
B59: =IFERROR(INDEX('Guest List'!$B$7:$B$206,MATCH(A59,'Guest List'!$A$7:$A$206,0)),"") | C59: 7 | H59: =IFERROR(INDEX('Guest List'!$B$7:$B$206,MATCH(G59,'Guest List'!$A$7:$A$206,0)),"") | I59: 7
B60: =IFERROR(INDEX('Guest List'!$B$7:$B$206,MATCH(A60,'Guest List'!$A$7:$A$206,0)),"") | C60: 8 | H60: =IFERROR(INDEX('Guest List'!$B$7:$B$206,MATCH(G60,'Guest List'!$A$7:$A$206,0)),"") | I60: 8
A66: Table 5 | G66: Table 6
A67: Capacity | B67: 8 | C67: Confirmed Seats | D67: =COUNTIFS(A70:A77,"<>") -> 0 | G67: Capacity | H67: 8 | I67: Confirmed Seats | J67: =COUNTIFS(A70:A77,"<>") -> 0
A68: Guest Tags Included | B68: =_xlfn.TEXTJOIN(", ",TRUE(),IF(COUNTIF(B70:B77,"Bride")>0,"Bride",""),IF(COUNTIF(B70:B77,"Groom")>0,"Groom",""),IF(COUNTIF(B70:B77,"Both")>0,"Both","")) | G68: Guest Tags Included | H68: =_xlfn.TEXTJOIN(", ",TRUE(),IF(COUNTIF(B70:B77,"Bride")>0,"Bride",""),IF(COUNTIF(B70:B77,"Groom")>0,"Groom",""),IF(COUNTIF(B70:B77,"Both")>0,"Both",""))
A69: Name | B69: Guest Tag | C69: # | G69: Name | H69: Guest Tag | I69: #
B70: =IFERROR(INDEX('Guest List'!$B$7:$B$206,MATCH(A70,'Guest List'!$A$7:$A$206,0)),"") | C70: 1 | H70: =IFERROR(INDEX('Guest List'!$B$7:$B$206,MATCH(G70,'Guest List'!$A$7:$A$206,0)),"") | I70: 1
B71: =IFERROR(INDEX('Guest List'!$B$7:$B$206,MATCH(A71,'Guest List'!$A$7:$A$206,0)),"") | C71: 2 | H71: =IFERROR(INDEX('Guest List'!$B$7:$B$206,MATCH(G71,'Guest List'!$A$7:$A$206,0)),"") | I71: 2
B72: =IFERROR(INDEX('Guest List'!$B$7:$B$206,MATCH(A72,'Guest List'!$A$7:$A$206,0)),"") | C72: 3 | H72: =IFERROR(INDEX('Guest List'!$B$7:$B$206,MATCH(G72,'Guest List'!$A$7:$A$206,0)),"") | I72: 3
B73: =IFERROR(INDEX('Guest List'!$B$7:$B$206,MATCH(A73,'Guest List'!$A$7:$A$206,0)),"") | C73: 4 | H73: =IFERROR(INDEX('Guest List'!$B$7:$B$206,MATCH(G73,'Guest List'!$A$7:$A$206,0)),"") | I73: 4
B74: =IFERROR(INDEX('Guest List'!$B$7:$B$206,MATCH(A74,'Guest List'!$A$7:$A$206,0)),"") | C74: 5 | H74: =IFERROR(INDEX('Guest List'!$B$7:$B$206,MATCH(G74,'Guest List'!$A$7:$A$206,0)),"") | I74: 5
B75: =IFERROR(INDEX('Guest List'!$B$7:$B$206,MATCH(A75,'Guest List'!$A$7:$A$206,0)),"") | C75: 6 | H75: =IFERROR(INDEX('Guest List'!$B$7:$B$206,MATCH(G75,'Guest List'!$A$7:$A$206,0)),"") | I75: 6
B76: =IFERROR(INDEX('Guest List'!$B$7:$B$206,MATCH(A76,'Guest List'!$A$7:$A$206,0)),"") | C76: 7 | H76: =IFERROR(INDEX('Guest List'!$B$7:$B$206,MATCH(G76,'Guest List'!$A$7:$A$206,0)),"") | I76: 7
B77: =IFERROR(INDEX('Guest List'!$B$7:$B$206,MATCH(A77,'Guest List'!$A$7:$A$206,0)),"") | C77: 8 | H77: =IFERROR(INDEX('Guest List'!$B$7:$B$206,MATCH(G77,'Guest List'!$A$7:$A$206,0)),"") | I77: 8
A83: Table 7 | G83: Table 8
A84: Capacity | B84: 8 | C84: Confirmed Seats | D84: =COUNTIFS(A87:A94,"<>") -> 0 | G84: Capacity | H84: 8 | I84: Confirmed Seats | J84: =COUNTIFS(A87:A94,"<>") -> 0
A85: Guest Tags Included | B85: =_xlfn.TEXTJOIN(", ",TRUE(),IF(COUNTIF(B87:B94,"Bride")>0,"Bride",""),IF(COUNTIF(B87:B94,"Groom")>0,"Groom",""),IF(COUNTIF(B87:B94,"Both")>0,"Both","")) | G85: Guest Tags Included | H85: =_xlfn.TEXTJOIN(", ",TRUE(),IF(COUNTIF(B87:B94,"Bride")>0,"Bride",""),IF(COUNTIF(B87:B94,"Groom")>0,"Groom",""),IF(COUNTIF(B87:B94,"Both")>0,"Both",""))
A86: Name | B86: Guest Tag | C86: # | G86: Name | H86: Guest Tag | I86: #
B87: =IFERROR(INDEX('Guest List'!$B$7:$B$206,MATCH(A87,'Guest List'!$A$7:$A$206,0)),"") | C87: 1 | H87: =IFERROR(INDEX('Guest List'!$B$7:$B$206,MATCH(G87,'Guest List'!$A$7:$A$206,0)),"") | I87: 1
B88: =IFERROR(INDEX('Guest List'!$B$7:$B$206,MATCH(A88,'Guest List'!$A$7:$A$206,0)),"") | C88: 2 | H88: =IFERROR(INDEX('Guest List'!$B$7:$B$206,MATCH(G88,'Guest List'!$A$7:$A$206,0)),"") | I88: 2
B89: =IFERROR(INDEX('Guest List'!$B$7:$B$206,MATCH(A89,'Guest List'!$A$7:$A$206,0)),"") | C89: 3 | H89: =IFERROR(INDEX('Guest List'!$B$7:$B$206,MATCH(G89,'Guest List'!$A$7:$A$206,0)),"") | I89: 3
B90: =IFERROR(INDEX('Guest List'!$B$7:$B$206,MATCH(A90,'Guest List'!$A$7:$A$206,0)),"") | C90: 4 | H90: =IFERROR(INDEX('Guest List'!$B$7:$B$206,MATCH(G90,'Guest List'!$A$7:$A$206,0)),"") | I90: 4
B91: =IFERROR(INDEX('Guest List'!$B$7:$B$206,MATCH(A91,'Guest List'!$A$7:$A$206,0)),"") | C91: 5 | H91: =IFERROR(INDEX('Guest List'!$B$7:$B$206,MATCH(G91,'Guest List'!$A$7:$A$206,0)),"") | I91: 5
B92: =IFERROR(INDEX('Guest List'!$B$7:$B$206,MATCH(A92,'Guest List'!$A$7:$A$206,0)),"") | C92: 6 | H92: =IFERROR(INDEX('Guest List'!$B$7:$B$206,MATCH(G92,'Guest List'!$A$7:$A$206,0)),"") | I92: 6
B93: =IFERROR(INDEX('Guest List'!$B$7:$B$206,MATCH(A93,'Guest List'!$A$7:$A$206,0)),"") | C93: 7 | H93: =IFERROR(INDEX('Guest List'!$B$7:$B$206,MATCH(G93,'Guest List'!$A$7:$A$206,0)),"") | I93: 7
B94: =IFERROR(INDEX('Guest List'!$B$7:$B$206,MATCH(A94,'Guest List'!$A$7:$A$206,0)),"") | C94: 8 | H94: =IFERROR(INDEX('Guest List'!$B$7:$B$206,MATCH(G94,'Guest List'!$A$7:$A$206,0)),"") | I94: 8
A100: Table 9 | G100: Table 10
A101: Capacity | B101: 8 | C101: Confirmed Seats | D101: =COUNTIFS(A104:A111,"<>") -> 0 | G101: Capacity | H101: 8 | I101: Confirmed Seats | J101: =COUNTIFS(A104:A111,"<>") -> 0
A102: Guest Tags Included | B102: =_xlfn.TEXTJOIN(", ",TRUE(),IF(COUNTIF(B104:B111,"Bride")>0,"Bride",""),IF(COUNTIF(B104:B111,"Groom")>0,"Groom",""),IF(COUNTIF(B104:B111,"Both")>0,"Both","")) | G102: Guest Tags Included | H102: =_xlfn.TEXTJOIN(", ",TRUE(),IF(COUNTIF(B104:B111,"Bride")>0,"Bride",""),IF(COUNTIF(B104:B111,"Groom")>0,"Groom",""),IF(COUNTIF(B104:B111,"Both")>0,"Both",""))
A103: Name | B103: Guest Tag | C103: # | G103: Name | H103: Guest Tag | I103: #
B104: =IFERROR(INDEX('Guest List'!$B$7:$B$206,MATCH(A104,'Guest List'!$A$7:$A$206,0)),"") | C104: 1 | H104: =IFERROR(INDEX('Guest List'!$B$7:$B$206,MATCH(G104,'Guest List'!$A$7:$A$206,0)),"") | I104: 1
B105: =IFERROR(INDEX('Guest List'!$B$7:$B$206,MATCH(A105,'Guest List'!$A$7:$A$206,0)),"") | C105: 2 | H105: =IFERROR(INDEX('Guest List'!$B$7:$B$206,MATCH(G105,'Guest List'!$A$7:$A$206,0)),"") | I105: 2
B106: =IFERROR(INDEX('Guest List'!$B$7:$B$206,MATCH(A106,'Guest List'!$A$7:$A$206,0)),"") | C106: 3 | H106: =IFERROR(INDEX('Guest List'!$B$7:$B$206,MATCH(G106,'Guest List'!$A$7:$A$206,0)),"") | I106: 3
B107: =IFERROR(INDEX('Guest List'!$B$7:$B$206,MATCH(A107,'Guest List'!$A$7:$A$206,0)),"") | C107: 4 | H107: =IFERROR(INDEX('Guest List'!$B$7:$B$206,MATCH(G107,'Guest List'!$A$7:$A$206,0)),"") | I107: 4
B108: =IFERROR(INDEX('Guest List'!$B$7:$B$206,MATCH(A108,'Guest List'!$A$7:$A$206,0)),"") | C108: 5 | H108: =IFERROR(INDEX('Guest List'!$B$7:$B$206,MATCH(G108,'Guest List'!$A$7:$A$206,0)),"") | I108: 5
B109: =IFERROR(INDEX('Guest List'!$B$7:$B$206,MATCH(A109,'Guest List'!$A$7:$A$206,0)),"") | C109: 6 | H109: =IFERROR(INDEX('Guest List'!$B$7:$B$206,MATCH(G109,'Guest List'!$A$7:$A$206,0)),"") | I109: 6
B110: =IFERROR(INDEX('Guest List'!$B$7:$B$206,MATCH(A110,'Guest List'!$A$7:$A$206,0)),"") | C110: 7 | H110: =IFERROR(INDEX('Guest List'!$B$7:$B$206,MATCH(G110,'Guest List'!$A$7:$A$206,0)),"") | I110: 7
B111: =IFERROR(INDEX('Guest List'!$B$7:$B$206,MATCH(A111,'Guest List'!$A$7:$A$206,0)),"") | C111: 8 | H111: =IFERROR(INDEX('Guest List'!$B$7:$B$206,MATCH(G111,'Guest List'!$A$7:$A$206,0)),"") | I111: 8

Sheet Rehearsal Dinner Seating
A1: REHEARSAL DINNER SEATING
A3: TOTAL SEATS | C3: CONFIRMED GUESTS | E3: CONFIRMED SEATS | G3: TENTATIVE SEATS | I3: REMAINING SEATS | K3: CONFIRMED TO BE SEATED
A4: =4*8 -> 32 | C4: =COUNTIFS('Guest List'!$F$7:$F$206,"Yes") -> 2 | E4: =COUNTIFS(D10:D29,"<>") -> 0 | G4: =COUNTIFS('Guest List'!$F$7:$F$206,"Awaited") -> 2 | I4: =A4-E4 -> 32 | K4: =IFERROR(E4/C4,0) -> 0
A6: Filter reference: Guest Tag / RSVP status are pulled live from the Guest List tab below.
A8: GUESTS WITHOUT A SEAT
A9: Name | B9: Guest Tag | C9: RSVP | D9: Table #
A10: =IF('Guest List'!$F7="Yes",'Guest List'!$A7,"") -> Alex Johnson | B10: =IF(A10<>"",'Guest List'!$B7,"") -> Bride | C10: =IF(A10<>"",'Guest List'!$F7,"") -> Yes
A11: =IF('Guest List'!$F8="Yes",'Guest List'!$A8,"") | B11: =IF(A11<>"",'Guest List'!$B8,"") | C11: =IF(A11<>"",'Guest List'!$F8,"")
A12: =IF('Guest List'!$F9="Yes",'Guest List'!$A9,"") | B12: =IF(A12<>"",'Guest List'!$B9,"") | C12: =IF(A12<>"",'Guest List'!$F9,"")
A13: =IF('Guest List'!$F10="Yes",'Guest List'!$A10,"") -> Morgan Kim | B13: =IF(A13<>"",'Guest List'!$B10,"") -> Bride | C13: =IF(A13<>"",'Guest List'!$F10,"") -> Yes
A14: =IF('Guest List'!$F11="Yes",'Guest List'!$A11,"") | B14: =IF(A14<>"",'Guest List'!$B11,"") | C14: =IF(A14<>"",'Guest List'!$F11,"")
A15: =IF('Guest List'!$F12="Yes",'Guest List'!$A12,"") | B15: =IF(A15<>"",'Guest List'!$B12,"") | C15: =IF(A15<>"",'Guest List'!$F12,"")
A16: =IF('Guest List'!$F13="Yes",'Guest List'!$A13,"") | B16: =IF(A16<>"",'Guest List'!$B13,"") | C16: =IF(A16<>"",'Guest List'!$F13,"")
A17: =IF('Guest List'!$F14="Yes",'Guest List'!$A14,"") | B17: =IF(A17<>"",'Guest List'!$B14,"") | C17: =IF(A17<>"",'Guest List'!$F14,"")
A18: =IF('Guest List'!$F15="Yes",'Guest List'!$A15,"") | B18: =IF(A18<>"",'Guest List'!$B15,"") | C18: =IF(A18<>"",'Guest List'!$F15,"")
A19: =IF('Guest List'!$F16="Yes",'Guest List'!$A16,"") | B19: =IF(A19<>"",'Guest List'!$B16,"") | C19: =IF(A19<>"",'Guest List'!$F16,"")
A20: =IF('Guest List'!$F17="Yes",'Guest List'!$A17,"") | B20: =IF(A20<>"",'Guest List'!$B17,"") | C20: =IF(A20<>"",'Guest List'!$F17,"")
A21: =IF('Guest List'!$F18="Yes",'Guest List'!$A18,"") | B21: =IF(A21<>"",'Guest List'!$B18,"") | C21: =IF(A21<>"",'Guest List'!$F18,"")
... A29: =IF('Guest List'!$F26="Yes",'Guest List'!$A26,"") | B29: =IF(A29<>"",'Guest List'!$B26,"") | C29: =IF(A29<>"",'Guest List'!$F26,"")
A31: TABLE BLOCKS
A32: Table 1 | G32: Table 2
A33: Capacity | B33: 8 | C33: Confirmed Seats | D33: =COUNTIFS(A36:A43,"<>") -> 0 | G33: Capacity | H33: 8 | I33: Confirmed Seats | J33: =COUNTIFS(A36:A43,"<>") -> 0
A34: Guest Tags Included | B34: =_xlfn.TEXTJOIN(", ",TRUE(),IF(COUNTIF(B36:B43,"Bride")>0,"Bride",""),IF(COUNTIF(B36:B43,"Groom")>0,"Groom",""),IF(COUNTIF(B36:B43,"Both")>0,"Both","")) | G34: Guest Tags Included | H34: =_xlfn.TEXTJOIN(", ",TRUE(),IF(COUNTIF(B36:B43,"Bride")>0,"Bride",""),IF(COUNTIF(B36:B43,"Groom")>0,"Groom",""),IF(COUNTIF(B36:B43,"Both")>0,"Both",""))
A35: Name | B35: Guest Tag | C35: # | G35: Name | H35: Guest Tag | I35: #
B36: =IFERROR(INDEX('Guest List'!$B$7:$B$206,MATCH(A36,'Guest List'!$A$7:$A$206,0)),"") | C36: 1 | H36: =IFERROR(INDEX('Guest List'!$B$7:$B$206,MATCH(G36,'Guest List'!$A$7:$A$206,0)),"") | I36: 1
B37: =IFERROR(INDEX('Guest List'!$B$7:$B$206,MATCH(A37,'Guest List'!$A$7:$A$206,0)),"") | C37: 2 | H37: =IFERROR(INDEX('Guest List'!$B$7:$B$206,MATCH(G37,'Guest List'!$A$7:$A$206,0)),"") | I37: 2
B38: =IFERROR(INDEX('Guest List'!$B$7:$B$206,MATCH(A38,'Guest List'!$A$7:$A$206,0)),"") | C38: 3 | H38: =IFERROR(INDEX('Guest List'!$B$7:$B$206,MATCH(G38,'Guest List'!$A$7:$A$206,0)),"") | I38: 3
B39: =IFERROR(INDEX('Guest List'!$B$7:$B$206,MATCH(A39,'Guest List'!$A$7:$A$206,0)),"") | C39: 4 | H39: =IFERROR(INDEX('Guest List'!$B$7:$B$206,MATCH(G39,'Guest List'!$A$7:$A$206,0)),"") | I39: 4
B40: =IFERROR(INDEX('Guest List'!$B$7:$B$206,MATCH(A40,'Guest List'!$A$7:$A$206,0)),"") | C40: 5 | H40: =IFERROR(INDEX('Guest List'!$B$7:$B$206,MATCH(G40,'Guest List'!$A$7:$A$206,0)),"") | I40: 5
B41: =IFERROR(INDEX('Guest List'!$B$7:$B$206,MATCH(A41,'Guest List'!$A$7:$A$206,0)),"") | C41: 6 | H41: =IFERROR(INDEX('Guest List'!$B$7:$B$206,MATCH(G41,'Guest List'!$A$7:$A$206,0)),"") | I41: 6
B42: =IFERROR(INDEX('Guest List'!$B$7:$B$206,MATCH(A42,'Guest List'!$A$7:$A$206,0)),"") | C42: 7 | H42: =IFERROR(INDEX('Guest List'!$B$7:$B$206,MATCH(G42,'Guest List'!$A$7:$A$206,0)),"") | I42: 7
B43: =IFERROR(INDEX('Guest List'!$B$7:$B$206,MATCH(A43,'Guest List'!$A$7:$A$206,0)),"") | C43: 8 | H43: =IFERROR(INDEX('Guest List'!$B$7:$B$206,MATCH(G43,'Guest List'!$A$7:$A$206,0)),"") | I43: 8
A49: Table 3 | G49: Table 4
A50: Capacity | B50: 8 | C50: Confirmed Seats | D50: =COUNTIFS(A53:A60,"<>") -> 0 | G50: Capacity | H50: 8 | I50: Confirmed Seats | J50: =COUNTIFS(A53:A60,"<>") -> 0
A51: Guest Tags Included | B51: =_xlfn.TEXTJOIN(", ",TRUE(),IF(COUNTIF(B53:B60,"Bride")>0,"Bride",""),IF(COUNTIF(B53:B60,"Groom")>0,"Groom",""),IF(COUNTIF(B53:B60,"Both")>0,"Both","")) | G51: Guest Tags Included | H51: =_xlfn.TEXTJOIN(", ",TRUE(),IF(COUNTIF(B53:B60,"Bride")>0,"Bride",""),IF(COUNTIF(B53:B60,"Groom")>0,"Groom",""),IF(COUNTIF(B53:B60,"Both")>0,"Both",""))
A52: Name | B52: Guest Tag | C52: # | G52: Name | H52: Guest Tag | I52: #
B53: =IFERROR(INDEX('Guest List'!$B$7:$B$206,MATCH(A53,'Guest List'!$A$7:$A$206,0)),"") | C53: 1 | H53: =IFERROR(INDEX('Guest List'!$B$7:$B$206,MATCH(G53,'Guest List'!$A$7:$A$206,0)),"") | I53: 1
B54: =IFERROR(INDEX('Guest List'!$B$7:$B$206,MATCH(A54,'Guest List'!$A$7:$A$206,0)),"") | C54: 2 | H54: =IFERROR(INDEX('Guest List'!$B$7:$B$206,MATCH(G54,'Guest List'!$A$7:$A$206,0)),"") | I54: 2
B55: =IFERROR(INDEX('Guest List'!$B$7:$B$206,MATCH(A55,'Guest List'!$A$7:$A$206,0)),"") | C55: 3 | H55: =IFERROR(INDEX('Guest List'!$B$7:$B$206,MATCH(G55,'Guest List'!$A$7:$A$206,0)),"") | I55: 3
B56: =IFERROR(INDEX('Guest List'!$B$7:$B$206,MATCH(A56,'Guest List'!$A$7:$A$206,0)),"") | C56: 4 | H56: =IFERROR(INDEX('Guest List'!$B$7:$B$206,MATCH(G56,'Guest List'!$A$7:$A$206,0)),"") | I56: 4
B57: =IFERROR(INDEX('Guest List'!$B$7:$B$206,MATCH(A57,'Guest List'!$A$7:$A$206,0)),"") | C57: 5 | H57: =IFERROR(INDEX('Guest List'!$B$7:$B$206,MATCH(G57,'Guest List'!$A$7:$A$206,0)),"") | I57: 5
B58: =IFERROR(INDEX('Guest List'!$B$7:$B$206,MATCH(A58,'Guest List'!$A$7:$A$206,0)),"") | C58: 6 | H58: =IFERROR(INDEX('Guest List'!$B$7:$B$206,MATCH(G58,'Guest List'!$A$7:$A$206,0)),"") | I58: 6
B59: =IFERROR(INDEX('Guest List'!$B$7:$B$206,MATCH(A59,'Guest List'!$A$7:$A$206,0)),"") | C59: 7 | H59: =IFERROR(INDEX('Guest List'!$B$7:$B$206,MATCH(G59,'Guest List'!$A$7:$A$206,0)),"") | I59: 7
B60: =IFERROR(INDEX('Guest List'!$B$7:$B$206,MATCH(A60,'Guest List'!$A$7:$A$206,0)),"") | C60: 8 | H60: =IFERROR(INDEX('Guest List'!$B$7:$B$206,MATCH(G60,'Guest List'!$A$7:$A$206,0)),"") | I60: 8

Sheet Wedding Registry
A1: WEDDING REGISTRY
A3: Item | B3: Store | C3: Link | D3: Price | E3: Priority | F3: Purchased | G3: Purchased By | H3: Thank You Sent
D4: 0 | E4: Medium | F4: =FALSE() -> 0 | H4: =FALSE() -> 0
D5: 0 | E5: Medium | F5: =FALSE() -> 0 | H5: =FALSE() -> 0
D6: 0 | E6: Medium | F6: =FALSE() -> 0 | H6: =FALSE() -> 0
D7: 0 | E7: Medium | F7: =FALSE() -> 0 | H7: =FALSE() -> 0
D8: 0 | E8: Medium | F8: =FALSE() -> 0 | H8: =FALSE() -> 0
D9: 0 | E9: Medium | F9: =FALSE() -> 0 | H9: =FALSE() -> 0
D10: 0 | E10: Medium | F10: =FALSE() -> 0 | H10: =FALSE() -> 0
D11: 0 | E11: Medium | F11: =FALSE() -> 0 | H11: =FALSE() -> 0
D12: 0 | E12: Medium | F12: =FALSE() -> 0 | H12: =FALSE() -> 0
D13: 0 | E13: Medium | F13: =FALSE() -> 0 | H13: =FALSE() -> 0
D14: 0 | E14: Medium | F14: =FALSE() -> 0 | H14: =FALSE() -> 0
D15: 0 | E15: Medium | F15: =FALSE() -> 0 | H15: =FALSE() -> 0
... D63: 0 | E63: Medium | F63: =FALSE() -> 0 | H63: =FALSE() -> 0

Sheet Wedding Party
A1: WEDDING PARTY
A3: CONFIRMED ROLES % | C3: # OF BRIDESMAIDS | E3: # OF GROOMSMEN | G3: ADDITIONAL PARTY | J3: Attire Status | K3: Count
A4: =IFERROR(COUNTIF(A9:A28,TRUE())/COUNTA(B9:B28),0) -> 1 | C4: =COUNTIF(C9:C28,"Bridesmaid") -> 0 | E4: =COUNTIF(C9:C28,"Groomsman") -> 0 | G4: =COUNTA(B9:B28)-COUNTIF(C9:C28,"Bridesmaid")-COUNTIF(C9:C28,"Groomsman") -> 2 | J4: Not Started | K4: =COUNTIFS($G$9:$G$28,J4) -> 20
J5: Ordered | K5: =COUNTIFS($G$9:$G$28,J5) -> 0
A6: Note: syncs with guest list. Add each wedding party member to the Guest List tab as well. | J6: Received | K6: =COUNTIFS($G$9:$G$28,J6) -> 0
J7: Fitting Scheduled | K7: =COUNTIFS($G$9:$G$28,J7) -> 0
A8: Confirmed | B8: Name | C8: Role | D8: Contact | E8: Email | F8: Attire | G8: Attire Status | H8: Notes | J8: Alterations Needed | K8: =COUNTIFS($G$9:$G$28,J8) -> 0
A9: =TRUE() -> 1 | B9: Jamie Lee | C9: Maid of Honor | G9: Not Started | J9: Ready | K9: =COUNTIFS($G$9:$G$28,J9) -> 0
A10: =TRUE() -> 1 | B10: Sam Rivera | C10: Best Man | G10: Not Started
A11: =FALSE() -> 0 | G11: Not Started
A12: =FALSE() -> 0 | G12: Not Started
A13: =FALSE() -> 0 | G13: Not Started
A14: =FALSE() -> 0 | G14: Not Started
A15: =FALSE() -> 0 | G15: Not Started
A16: =FALSE() -> 0 | G16: Not Started
A17: =FALSE() -> 0 | G17: Not Started
A18: =FALSE() -> 0 | G18: Not Started
A19: =FALSE() -> 0 | G19: Not Started
A20: =FALSE() -> 0 | G20: Not Started
A21: =FALSE() -> 0 | G21: Not Started
A22: =FALSE() -> 0 | G22: Not Started
... A28: =FALSE() -> 0 | G28: Not Started

Sheet Aisle Order
A1: AISLE ORDER
A3: BRIDE'S SIDE | C3: GROOM'S SIDE
A4: Role | B4: Name | C4: Role | D4: Name
A19: ANYONE ELSE

Sheet Wedding Party Gifts
A1: WEDDING PARTY GIFTS
A3: TOTAL GIFTS | C3: TOTAL COST | E3: NEED TO BUY | G3: PURCHASED | I3: NEED TO WRAP | K3: GIVEN
A4: =COUNTA(B7:B26) -> 0 | C4: =SUM(G7:G26) -> 0 | E4: =COUNTIF(H7:H26,"Need to Buy") -> 20 | G4: =COUNTIF(H7:H26,"Purchased") -> 0 | I4: =COUNTIFS(H7:H26,"Purchased",I7:I26,FALSE()) -> 0 | K4: =COUNTIF(I7:I26,TRUE()) -> 0
A6: Role | B6: Gift | C6: Store | D6: Link | E6: Cost per Unit | F6: Qty | G6: Total Cost | H6: Status | I6: Given | J6: Note
E7: 0 | F7: 1 | G7: =E7*F7 -> 0 | H7: Need to Buy | I7: =FALSE() -> 0
E8: 0 | F8: 1 | G8: =E8*F8 -> 0 | H8: Need to Buy | I8: =FALSE() -> 0
E9: 0 | F9: 1 | G9: =E9*F9 -> 0 | H9: Need to Buy | I9: =FALSE() -> 0
E10: 0 | F10: 1 | G10: =E10*F10 -> 0 | H10: Need to Buy | I10: =FALSE() -> 0
E11: 0 | F11: 1 | G11: =E11*F11 -> 0 | H11: Need to Buy | I11: =FALSE() -> 0
E12: 0 | F12: 1 | G12: =E12*F12 -> 0 | H12: Need to Buy | I12: =FALSE() -> 0
E13: 0 | F13: 1 | G13: =E13*F13 -> 0 | H13: Need to Buy | I13: =FALSE() -> 0
E14: 0 | F14: 1 | G14: =E14*F14 -> 0 | H14: Need to Buy | I14: =FALSE() -> 0
E15: 0 | F15: 1 | G15: =E15*F15 -> 0 | H15: Need to Buy | I15: =FALSE() -> 0
E16: 0 | F16: 1 | G16: =E16*F16 -> 0 | H16: Need to Buy | I16: =FALSE() -> 0
E17: 0 | F17: 1 | G17: =E17*F17 -> 0 | H17: Need to Buy | I17: =FALSE() -> 0
E18: 0 | F18: 1 | G18: =E18*F18 -> 0 | H18: Need to Buy | I18: =FALSE() -> 0
... E26: 0 | F26: 1 | G26: =E26*F26 -> 0 | H26: Need to Buy | I26: =FALSE() -> 0

Sheet Moodboard
A1: MOODBOARD 1
A3: Paste inspiration images below (Insert > Image > Cell), and note the source link underneath each.
A5: [ image ] | C5: [ image ] | E5: [ image ]
A11: Source URL: | C11: Source URL: | E11: Source URL:
A13: [ image ] | C13: [ image ] | E13: [ image ]
A19: Source URL: | C19: Source URL: | E19: Source URL:

Sheet Decor Inventory
A1: DECOR INVENTORY
A3: TOTAL COST | C3: CONFIRMED | E3: TO BE DECIDED | G3: CANCELLED | K3: Location | L3: Confirmed Cost
A4: =SUMIFS(H7:H46,D7:D46,"Confirmed") -> 0 | C4: =COUNTIF(D7:D46,"Confirmed") -> 0 | E4: =COUNTIF(D7:D46,"To Be Decided") -> 40 | G4: =COUNTIF(D7:D46,"Cancelled") -> 0 | K4: Ceremony | L4: =SUMIFS($H$7:$H$46,$B$7:$B$46,K4,$D$7:$D$46,"Confirmed") -> 0
K5: Cocktail Hour | L5: =SUMIFS($H$7:$H$46,$B$7:$B$46,K5,$D$7:$D$46,"Confirmed") -> 0
A6: Item | B6: Decor Location | C6: Vendor | D6: Status | E6: Buy/Rent | F6: Cost per Unit | G6: Quantity | H6: Total Cost | I6: Image URL | K6: Reception Entrance | L6: =SUMIFS($H$7:$H$46,$B$7:$B$46,K6,$D$7:$D$46,"Confirmed") -> 0
D7: To Be Decided | F7: 0 | G7: 1 | H7: =F7*G7 -> 0 | K7: Reception Tables | L7: =SUMIFS($H$7:$H$46,$B$7:$B$46,K7,$D$7:$D$46,"Confirmed") -> 0
D8: To Be Decided | F8: 0 | G8: 1 | H8: =F8*G8 -> 0 | K8: Head Table | L8: =SUMIFS($H$7:$H$46,$B$7:$B$46,K8,$D$7:$D$46,"Confirmed") -> 0
D9: To Be Decided | F9: 0 | G9: 1 | H9: =F9*G9 -> 0 | K9: Cake Table | L9: =SUMIFS($H$7:$H$46,$B$7:$B$46,K9,$D$7:$D$46,"Confirmed") -> 0
D10: To Be Decided | F10: 0 | G10: 1 | H10: =F10*G10 -> 0 | K10: Photo Booth | L10: =SUMIFS($H$7:$H$46,$B$7:$B$46,K10,$D$7:$D$46,"Confirmed") -> 0
D11: To Be Decided | F11: 0 | G11: 1 | H11: =F11*G11 -> 0 | K11: Restrooms | L11: =SUMIFS($H$7:$H$46,$B$7:$B$46,K11,$D$7:$D$46,"Confirmed") -> 0
D12: To Be Decided | F12: 0 | G12: 1 | H12: =F12*G12 -> 0 | K12: Other | L12: =SUMIFS($H$7:$H$46,$B$7:$B$46,K12,$D$7:$D$46,"Confirmed") -> 0
D13: To Be Decided | F13: 0 | G13: 1 | H13: =F13*G13 -> 0
D14: To Be Decided | F14: 0 | G14: 1 | H14: =F14*G14 -> 0
D15: To Be Decided | F15: 0 | G15: 1 | H15: =F15*G15 -> 0
D16: To Be Decided | F16: 0 | G16: 1 | H16: =F16*G16 -> 0
D17: To Be Decided | F17: 0 | G17: 1 | H17: =F17*G17 -> 0
D18: To Be Decided | F18: 0 | G18: 1 | H18: =F18*G18 -> 0
D19: To Be Decided | F19: 0 | G19: 1 | H19: =F19*G19 -> 0
D20: To Be Decided | F20: 0 | G20: 1 | H20: =F20*G20 -> 0
D21: To Be Decided | F21: 0 | G21: 1 | H21: =F21*G21 -> 0
D22: To Be Decided | F22: 0 | G22: 1 | H22: =F22*G22 -> 0
D23: To Be Decided | F23: 0 | G23: 1 | H23: =F23*G23 -> 0
D24: To Be Decided | F24: 0 | G24: 1 | H24: =F24*G24 -> 0
... D46: To Be Decided | F46: 0 | G46: 1 | H46: =F46*G46 -> 0

Sheet Flower Arrangements
A1: FLOWER ARRANGEMENTS
A3: # OF ARRANGEMENTS | D3: TOTAL COST | K3: Florist | L3: Cost
A4: =COUNTA(A7:A36) -> 8 | D4: =SUM(E7:E36) -> 0 | K4: ='Vendor Selection'!C6 -> Name | L4: =SUM(E7:E36) -> 0
A6: Item | B6: Florist | C6: Cost per Unit | D6: Quantity | E6: Total Cost | F6: Status | G6: Flowers Needed | H6: Notes | I6: Image URL
A7: Bridal Bouquet | C7: 0 | D7: 1 | E7: =C7*D7 -> 0 | F7: Not Started
A8: Bridesmaid Bouquets | C8: 0 | D8: 1 | E8: =C8*D8 -> 0 | F8: Not Started
A9: Boutonnieres | C9: 0 | D9: 1 | E9: =C9*D9 -> 0 | F9: Not Started
A10: Corsages | C10: 0 | D10: 1 | E10: =C10*D10 -> 0 | F10: Not Started
A11: Ceremony Arch Florals | C11: 0 | D11: 1 | E11: =C11*D11 -> 0 | F11: Not Started
A12: Centerpieces | C12: 0 | D12: 1 | E12: =C12*D12 -> 0 | F12: Not Started
A13: Aisle Decor | C13: 0 | D13: 1 | E13: =C13*D13 -> 0 | F13: Not Started
A14: Cake Florals | C14: 0 | D14: 1 | E14: =C14*D14 -> 0 | F14: Not Started
C15: 0 | D15: 1 | E15: =C15*D15 -> 0 | F15: Not Started
C16: 0 | D16: 1 | E16: =C16*D16 -> 0 | F16: Not Started
C17: 0 | D17: 1 | E17: =C17*D17 -> 0 | F17: Not Started
C18: 0 | D18: 1 | E18: =C18*D18 -> 0 | F18: Not Started
C19: 0 | D19: 1 | E19: =C19*D19 -> 0 | F19: Not Started
C20: 0 | D20: 1 | E20: =C20*D20 -> 0 | F20: Not Started
C21: 0 | D21: 1 | E21: =C21*D21 -> 0 | F21: Not Started
C22: 0 | D22: 1 | E22: =C22*D22 -> 0 | F22: Not Started
C23: 0 | D23: 1 | E23: =C23*D23 -> 0 | F23: Not Started
C24: 0 | D24: 1 | E24: =C24*D24 -> 0 | F24: Not Started
C25: 0 | D25: 1 | E25: =C25*D25 -> 0 | F25: Not Started
C26: 0 | D26: 1 | E26: =C26*D26 -> 0 | F26: Not Started
... C36: 0 | D36: 1 | E36: =C36*D36 -> 0 | F36: Not Started

Sheet Attire and Makeup
A1: ATTIRE AND MAKEUP
A3: SETUP
A4: Event | B4: For Person / Role | C4: Category | D4: Notes
A17: PHOTO REFERENCE GALLERY
A18: Image URL | B18: Event | C18: For Person / Role | D18: Category | E18: Notes

Sheet Accommodation
A1: WEDDING LOGISTICS: ACCOMMODATION
A3: GUESTS STILL NEEDING A ROOM
A4: Confirmed Guest | B4: Has Room?
A5: =IF('Guest List'!$F7="Yes",'Guest List'!$A7,"") -> Alex Johnson | B5: =IF(A5="","",IF(COUNTIF(A38:A67,A5)>0,"Yes","No")) -> No
A6: =IF('Guest List'!$F8="Yes",'Guest List'!$A8,"") | B6: =IF(A6="","",IF(COUNTIF(A38:A67,A6)>0,"Yes","No"))
A7: =IF('Guest List'!$F9="Yes",'Guest List'!$A9,"") | B7: =IF(A7="","",IF(COUNTIF(A38:A67,A7)>0,"Yes","No"))
A8: =IF('Guest List'!$F10="Yes",'Guest List'!$A10,"") -> Morgan Kim | B8: =IF(A8="","",IF(COUNTIF(A38:A67,A8)>0,"Yes","No")) -> No
A9: =IF('Guest List'!$F11="Yes",'Guest List'!$A11,"") | B9: =IF(A9="","",IF(COUNTIF(A38:A67,A9)>0,"Yes","No"))
A10: =IF('Guest List'!$F12="Yes",'Guest List'!$A12,"") | B10: =IF(A10="","",IF(COUNTIF(A38:A67,A10)>0,"Yes","No"))
A11: =IF('Guest List'!$F13="Yes",'Guest List'!$A13,"") | B11: =IF(A11="","",IF(COUNTIF(A38:A67,A11)>0,"Yes","No"))
A12: =IF('Guest List'!$F14="Yes",'Guest List'!$A14,"") | B12: =IF(A12="","",IF(COUNTIF(A38:A67,A12)>0,"Yes","No"))
A13: =IF('Guest List'!$F15="Yes",'Guest List'!$A15,"") | B13: =IF(A13="","",IF(COUNTIF(A38:A67,A13)>0,"Yes","No"))
A14: =IF('Guest List'!$F16="Yes",'Guest List'!$A16,"") | B14: =IF(A14="","",IF(COUNTIF(A38:A67,A14)>0,"Yes","No"))
A15: =IF('Guest List'!$F17="Yes",'Guest List'!$A17,"") | B15: =IF(A15="","",IF(COUNTIF(A38:A67,A15)>0,"Yes","No"))
A16: =IF('Guest List'!$F18="Yes",'Guest List'!$A18,"") | B16: =IF(A16="","",IF(COUNTIF(A38:A67,A16)>0,"Yes","No"))
A17: =IF('Guest List'!$F19="Yes",'Guest List'!$A19,"") | B17: =IF(A17="","",IF(COUNTIF(A38:A67,A17)>0,"Yes","No"))
A18: =IF('Guest List'!$F20="Yes",'Guest List'!$A20,"") | B18: =IF(A18="","",IF(COUNTIF(A38:A67,A18)>0,"Yes","No"))
A19: =IF('Guest List'!$F21="Yes",'Guest List'!$A21,"") | B19: =IF(A19="","",IF(COUNTIF(A38:A67,A19)>0,"Yes","No"))
A20: =IF('Guest List'!$F22="Yes",'Guest List'!$A22,"") | B20: =IF(A20="","",IF(COUNTIF(A38:A67,A20)>0,"Yes","No"))
A21: =IF('Guest List'!$F23="Yes",'Guest List'!$A23,"") | B21: =IF(A21="","",IF(COUNTIF(A38:A67,A21)>0,"Yes","No"))
A22: =IF('Guest List'!$F24="Yes",'Guest List'!$A24,"") | B22: =IF(A22="","",IF(COUNTIF(A38:A67,A22)>0,"Yes","No"))
A23: =IF('Guest List'!$F25="Yes",'Guest List'!$A25,"") | B23: =IF(A23="","",IF(COUNTIF(A38:A67,A23)>0,"Yes","No"))
A24: =IF('Guest List'!$F26="Yes",'Guest List'!$A26,"") | B24: =IF(A24="","",IF(COUNTIF(A38:A67,A24)>0,"Yes","No"))
A25: =IF('Guest List'!$F27="Yes",'Guest List'!$A27,"") | B25: =IF(A25="","",IF(COUNTIF(A38:A67,A25)>0,"Yes","No"))
A26: =IF('Guest List'!$F28="Yes",'Guest List'!$A28,"") | B26: =IF(A26="","",IF(COUNTIF(A38:A67,A26)>0,"Yes","No"))
A27: =IF('Guest List'!$F29="Yes",'Guest List'!$A29,"") | B27: =IF(A27="","",IF(COUNTIF(A38:A67,A27)>0,"Yes","No"))
A28: =IF('Guest List'!$F30="Yes",'Guest List'!$A30,"") | B28: =IF(A28="","",IF(COUNTIF(A38:A67,A28)>0,"Yes","No"))
A29: =IF('Guest List'!$F31="Yes",'Guest List'!$A31,"") | B29: =IF(A29="","",IF(COUNTIF(A38:A67,A29)>0,"Yes","No"))
A30: =IF('Guest List'!$F32="Yes",'Guest List'!$A32,"") | B30: =IF(A30="","",IF(COUNTIF(A38:A67,A30)>0,"Yes","No"))
A31: =IF('Guest List'!$F33="Yes",'Guest List'!$A33,"") | B31: =IF(A31="","",IF(COUNTIF(A38:A67,A31)>0,"Yes","No"))
A32: =IF('Guest List'!$F34="Yes",'Guest List'!$A34,"") | B32: =IF(A32="","",IF(COUNTIF(A38:A67,A32)>0,"Yes","No"))
A33: =IF('Guest List'!$F35="Yes",'Guest List'!$A35,"") | B33: =IF(A33="","",IF(COUNTIF(A38:A67,A33)>0,"Yes","No"))
A34: =IF('Guest List'!$F36="Yes",'Guest List'!$A36,"") | B34: =IF(A34="","",IF(COUNTIF(A38:A67,A34)>0,"Yes","No"))
A36: HOTEL ACCOMMODATION
A37: Guest Name | B37: Accommodation Name | C37: Room Number | D37: Check-in Date/Time | E37: Check-out Date/Time

Sheet Transportation
A1: WEDDING LOGISTICS: TRANSPORTATION
A3: Transportation For | B3: Vendor Name | C3: Vendor Contact | D3: Pickup Location | E3: Dropoff Location | F3: Pickup Date | G3: Pickup Time | H3: Notes

Sheet Stationery Checklist
A1: WEDDING STATIONERY: CHECKLIST
A3: PROGRESS | M3: Design Status | N3: Count
A4: =IFERROR(COUNTIF(F7:F26,TRUE())/COUNTA(B7:B26),0) -> 0 | M4: Not Started | N4: =COUNTIF($D$7:$D$26,M4) -> 20
M5: In Progress | N5: =COUNTIF($D$7:$D$26,M5) -> 0
A6: Category | B6: Item Name | C6: Quantity | D6: Design Status | E6: Printing Status | F6: Overall Status | G6: Vendor / Source | H6: Due Date | I6: Total Design Cost | J6: Print Cost per Unit | K6: Total Cost | M6: Completed | N6: =COUNTIF($D$7:$D$26,M6) -> 0
B7: Save the Dates | C7: 1 | D7: Not Started | E7: Not Ordered | F7: =FALSE() -> 0 | I7: 0 | J7: 0 | K7: =I7+(J7*C7) -> 0
B8: Invitation Suite | C8: 1 | D8: Not Started | E8: Not Ordered | F8: =FALSE() -> 0 | I8: 0 | J8: 0 | K8: =I8+(J8*C8) -> 0 | M8: Print Status | N8: Count
B9: RSVP Cards | C9: 1 | D9: Not Started | E9: Not Ordered | F9: =FALSE() -> 0 | I9: 0 | J9: 0 | K9: =I9+(J9*C9) -> 0 | M9: Not Needed | N9: =COUNTIF($E$7:$E$26,M9) -> 0
B10: Ceremony Programs | C10: 1 | D10: Not Started | E10: Not Ordered | F10: =FALSE() -> 0 | I10: 0 | J10: 0 | K10: =I10+(J10*C10) -> 0 | M10: Not Ordered | N10: =COUNTIF($E$7:$E$26,M10) -> 20
B11: Menu Cards | C11: 1 | D11: Not Started | E11: Not Ordered | F11: =FALSE() -> 0 | I11: 0 | J11: 0 | K11: =I11+(J11*C11) -> 0 | M11: Ordered | N11: =COUNTIF($E$7:$E$26,M11) -> 0
B12: Place Cards | C12: 1 | D12: Not Started | E12: Not Ordered | F12: =FALSE() -> 0 | I12: 0 | J12: 0 | K12: =I12+(J12*C12) -> 0 | M12: Printed | N12: =COUNTIF($E$7:$E$26,M12) -> 0
B13: Table Numbers | C13: 1 | D13: Not Started | E13: Not Ordered | F13: =FALSE() -> 0 | I13: 0 | J13: 0 | K13: =I13+(J13*C13) -> 0
B14: Welcome Sign | C14: 1 | D14: Not Started | E14: Not Ordered | F14: =FALSE() -> 0 | I14: 0 | J14: 0 | K14: =I14+(J14*C14) -> 0 | M14: Category | N14: Cost
B15: Thank You Cards | C15: 1 | D15: Not Started | E15: Not Ordered | F15: =FALSE() -> 0 | I15: 0 | J15: 0 | K15: =I15+(J15*C15) -> 0 | M15: Before the Wedding | N15: =SUMIFS($K$7:$K$26,$A$7:$A$26,M15) -> 0
B16: Seating Chart | C16: 1 | D16: Not Started | E16: Not Ordered | F16: =FALSE() -> 0 | I16: 0 | J16: 0 | K16: =I16+(J16*C16) -> 0 | M16: Wedding Day | N16: =SUMIFS($K$7:$K$26,$A$7:$A$26,M16) -> 0
C17: 1 | D17: Not Started | E17: Not Ordered | F17: =FALSE() -> 0 | I17: 0 | J17: 0 | K17: =I17+(J17*C17) -> 0 | M17: After the Wedding | N17: =SUMIFS($K$7:$K$26,$A$7:$A$26,M17) -> 0
C18: 1 | D18: Not Started | E18: Not Ordered | F18: =FALSE() -> 0 | I18: 0 | J18: 0 | K18: =I18+(J18*C18) -> 0
C19: 1 | D19: Not Started | E19: Not Ordered | F19: =FALSE() -> 0 | I19: 0 | J19: 0 | K19: =I19+(J19*C19) -> 0
C20: 1 | D20: Not Started | E20: Not Ordered | F20: =FALSE() -> 0 | I20: 0 | J20: 0 | K20: =I20+(J20*C20) -> 0
C21: 1 | D21: Not Started | E21: Not Ordered | F21: =FALSE() -> 0 | I21: 0 | J21: 0 | K21: =I21+(J21*C21) -> 0
C22: 1 | D22: Not Started | E22: Not Ordered | F22: =FALSE() -> 0 | I22: 0 | J22: 0 | K22: =I22+(J22*C22) -> 0
C23: 1 | D23: Not Started | E23: Not Ordered | F23: =FALSE() -> 0 | I23: 0 | J23: 0 | K23: =I23+(J23*C23) -> 0
C24: 1 | D24: Not Started | E24: Not Ordered | F24: =FALSE() -> 0 | I24: 0 | J24: 0 | K24: =I24+(J24*C24) -> 0
C25: 1 | D25: Not Started | E25: Not Ordered | F25: =FALSE() -> 0 | I25: 0 | J25: 0 | K25: =I25+(J25*C25) -> 0
C26: 1 | D26: Not Started | E26: Not Ordered | F26: =FALSE() -> 0 | I26: 0 | J26: 0 | K26: =I26+(J26*C26) -> 0

Sheet Save the Date
A1: SAVE THE DATE
A3: Fully Automated | C3: 3 Options | E3: Ready to Share
A4: [ Save the Date mockup 1 ] | C4: [ Save the Date mockup 2 ] | E4: [ Save the Date mockup 3 ]
A14: WORDING NOTES
A15: Draft your save the date wording here.
A20: MAILING TIMELINE NOTES
A21: Save the dates typically mail 6 to 8 months before the wedding, sooner for destination weddings.

Sheet Engagement Party
A1: PRE-WEDDING: ENGAGEMENT PARTY
A3: OVERVIEW
A4: Date | C4: Time | E4: Venue | G4: Theme
A5: Budget | B5: 2000
A7: COUNTDOWN | C7: LEFT TO SPEND | E7: LEFT TO BUDGET
A8: =IFERROR('Get Started'!$C$4-TODAY(),"") -> 300 | C8: =D18 -> 0 | E8: =B18-C18 -> 0
A10: EXPENSE SUMMARY
A11: Category | B11: Budget | C11: Actual | D11: Left
A12: Venue | B12: 0 | C12: 0 | D12: =B12-C12 -> 0
A13: Food and Drinks | B13: 0 | C13: 0 | D13: =B13-C13 -> 0
A14: Decor | B14: 0 | C14: 0 | D14: =B14-C14 -> 0
A15: Invitations | B15: 0 | C15: 0 | D15: =B15-C15 -> 0
A16: Favors | B16: 0 | C16: 0 | D16: =B16-C16 -> 0
A17: Other | B17: 0 | C17: 0 | D17: =B17-C17 -> 0
A18: Total | B18: =SUM(B12:B17) -> 0 | C18: =SUM(C12:C17) -> 0 | D18: =SUM(D12:D17) -> 0
A20: GUEST LIST AND RSVP
A21: Name | B21: RSVP | C21: Notes

Sheet Bridal Shower
A1: PRE-WEDDING: BRIDAL SHOWER
A3: OVERVIEW
A4: Date | C4: Time | E4: Venue | G4: Theme
A5: Budget | B5: 1200
A7: COUNTDOWN | C7: LEFT TO SPEND | E7: LEFT TO BUDGET
A8: =IFERROR('Get Started'!$C$4-TODAY(),"") -> 300 | C8: =D18 -> 0 | E8: =B18-C18 -> 0
A10: EXPENSE SUMMARY
A11: Category | B11: Budget | C11: Actual | D11: Left
A12: Venue | B12: 0 | C12: 0 | D12: =B12-C12 -> 0
A13: Food and Drinks | B13: 0 | C13: 0 | D13: =B13-C13 -> 0
A14: Decor | B14: 0 | C14: 0 | D14: =B14-C14 -> 0
A15: Games and Activities | B15: 0 | C15: 0 | D15: =B15-C15 -> 0
A16: Favors | B16: 0 | C16: 0 | D16: =B16-C16 -> 0
A17: Other | B17: 0 | C17: 0 | D17: =B17-C17 -> 0
A18: Total | B18: =SUM(B12:B17) -> 0 | C18: =SUM(C12:C17) -> 0 | D18: =SUM(D12:D17) -> 0
A20: GUEST LIST AND RSVP
A21: Name | B21: RSVP | C21: Notes

Sheet Bachelor(ette) Planner
A1: PRE-WEDDING: BACHELOR(ETTE) PLANNER
A3: OVERVIEW
A4: Type | B4: Party | C4: Date / # of Days | E4: Venue / Location | G4: Budget | H4: 1500
A6: CONFIRMED GUESTS | C6: LEFT TO BUDGET
A7: =COUNTIF(B11:B35,"Yes") -> 0 | C7: =B65-C65 -> 0
A9: GUEST LIST AND RSVP
A10: ITINERARY
A11: Date | B11: Time | C11: Details
A23: BOOKINGS (ACCOMMODATION OPTIONS)
A24: Option | B24: Name | C24: Phone | D24: Email | E24: Booking Date | F24: Duration | G24: Status | H24: Payment Info | I24: Reference
A25: Option 1
A26: Option 2
A28: TRAVEL ARRANGEMENT
A29: Traveler | B29: Mode | C29: Departure | D29: Arrival | E29: Confirmation # | F29: Notes
A39: EXPENSE TRACKER
A40: Date | B40: Amount | C40: Category | D40: Note
A57: EXPENSE SUMMARY
A58: Category | B58: Budget | C58: Actual | D58: Left
A59: Accommodation | B59: 0 | C59: 0 | D59: =B59-C59 -> 0
A60: Travel | B60: 0 | C60: 0 | D60: =B60-C60 -> 0
A61: Activities | B61: 0 | C61: 0 | D61: =B61-C61 -> 0
A62: Food and Drinks | B62: 0 | C62: 0 | D62: =B62-C62 -> 0
A63: Attire | B63: 0 | C63: 0 | D63: =B63-C63 -> 0
A64: Other | B64: 0 | C64: 0 | D64: =B64-C64 -> 0
A65: Total | B65: =SUM(B59:B64) -> 0 | C65: =SUM(C59:C64) -> 0 | D65: =SUM(D59:D64) -> 0

Sheet Honeymoon Planner
A1: HONEYMOON PLANNER
A3: TOTAL SPENT | C3: LEFT TO SPEND
A4: =C15 -> 0 | C4: =B15-C15 -> 0
A6: EXPENSES TRACKER
A7: Category | B7: Budget | C7: Actual | D7: Left
A8: Flights | B8: 0 | C8: 0 | D8: =B8-C8 -> 0
A9: Accommodation | B9: 0 | C9: 0 | D9: =B9-C9 -> 0
A10: Food and Drinks | B10: 0 | C10: 0 | D10: =B10-C10 -> 0
A11: Activities and Excursions | B11: 0 | C11: 0 | D11: =B11-C11 -> 0
A12: Shopping | B12: 0 | C12: 0 | D12: =B12-C12 -> 0
A13: Transportation | B13: 0 | C13: 0 | D13: =B13-C13 -> 0
A14: Other | B14: 0 | C14: 0 | D14: =B14-C14 -> 0
A15: Total | B15: =SUM(B8:B14) -> 0 | C15: =SUM(C8:C14) -> 0 | D15: =SUM(D8:D14) -> 0
A17: CURRENCY CALCULATOR
A18: From Currency | B18: To Currency | C18: Exchange Rate | D18: Amount | E18: Converted Amount
A19: USD | B19: EUR | C19: 0.92 | D19: 100 | E19: =D19*C19 -> 92
A22: TRANSACTION TRACKER
A23: Date | B23: Amount | C23: Category | D23: Note
A45: BOOKINGS (ACCOMMODATION OPTIONS)
A46: Option | B46: Name | C46: Phone | D46: Email | E46: Booking Date | F46: Duration | G46: Status | H46: Reference
A47: Option 1
A48: Option 2
A50: TRAVEL ARRANGEMENT
A51: Traveler | B51: Mode | C51: Departure | D51: Arrival | E51: Confirmation # | F51: Notes
A60: HONEYMOON CHECKLIST
A61: Done | B61: Task | C61: Assigned To | F61: Status | G61: Count | I61: Assigned To | J61: Incomplete
A62: =FALSE() -> 0 | B62: Book flights | C62: Both | F62: Done | G62: =COUNTIF(A62:A71,TRUE()) -> 0 | I62: Bride | J62: =COUNTIFS($C$62:$C$71,I62,$A$62:$A$71,FALSE()) -> 0
A63: =FALSE() -> 0 | B63: Book accommodation | C63: Both | F63: Incomplete | G63: =COUNTIF(A62:A71,FALSE()) -> 10 | I63: Groom | J63: =COUNTIFS($C$62:$C$71,I63,$A$62:$A$71,FALSE()) -> 0
A64: =FALSE() -> 0 | B64: Confirm passport validity | C64: Both | I64: Both | J64: =COUNTIFS($C$62:$C$71,I64,$A$62:$A$71,FALSE()) -> 10
A65: =FALSE() -> 0 | B65: Arrange travel insurance | C65: Both | I65: Wedding Planner | J65: =COUNTIFS($C$62:$C$71,I65,$A$62:$A$71,FALSE()) -> 0
A66: =FALSE() -> 0 | B66: Notify bank of travel dates | C66: Both | I66: Maid of Honor | J66: =COUNTIFS($C$62:$C$71,I66,$A$62:$A$71,FALSE()) -> 0
A67: =FALSE() -> 0 | B67: Exchange currency | C67: Both | I67: Best Man | J67: =COUNTIFS($C$62:$C$71,I67,$A$62:$A$71,FALSE()) -> 0
A68: =FALSE() -> 0 | B68: Confirm excursion reservations | C68: Both | I68: Parent | J68: =COUNTIFS($C$62:$C$71,I68,$A$62:$A$71,FALSE()) -> 0
A69: =FALSE() -> 0 | B69: Pack luggage | C69: Both | I69: Other | J69: =COUNTIFS($C$62:$C$71,I69,$A$62:$A$71,FALSE()) -> 0
A70: =FALSE() -> 0 | B70: Print travel documents | C70: Both
A71: =FALSE() -> 0 | B71: Arrange airport transportation | C71: Both
A74: Packing list reference: see the Packing List tab, Honeymoon section.

Sheet Gifts and Thank You
A1: GIFTS AND THANK YOU
A3: THANK YOU CARDS SENT
A4: =IFERROR(COUNTIF(D7:D206,TRUE())&" / "&COUNTA(A7:A206),"0 / 0") -> 0 / 0
A6: Guest Name | B6: Gift Received | C6: Estimated Value | D6: Thank You Card Sent | E6: Date Sent | F6: Notes
C7: 0 | D7: =FALSE() -> 0
C8: 0 | D8: =FALSE() -> 0
C9: 0 | D9: =FALSE() -> 0
C10: 0 | D10: =FALSE() -> 0
C11: 0 | D11: =FALSE() -> 0
C12: 0 | D12: =FALSE() -> 0
C13: 0 | D13: =FALSE() -> 0
C14: 0 | D14: =FALSE() -> 0
C15: 0 | D15: =FALSE() -> 0
C16: 0 | D16: =FALSE() -> 0
C17: 0 | D17: =FALSE() -> 0
C18: 0 | D18: =FALSE() -> 0
... C206: 0 | D206: =FALSE() -> 0

Sheet Lists
A1: AssignedTo | B1: Priority | C1: YesNo | D1: YesNoAwaited | E1: GuestTag | F1: GuestType | G1: MealPref | H1: VendorCategory | I1: AttireStatus | J1: WeddingPartyRole | K1: GiftStatus | L1: DecorLocation | M1: DecorStatus | N1: BuyRent | O1: FloralStatus | P1: AttireCategory | Q1: AccommodationList | R1: StationeryCategory | S1: DesignStatus | T1: PrintStatus | U1: PaymentStatus | V1: PaymentType | W1: TrueFalse | X1: BachelorType | Y1: CurrencyList | Z1: BookingStatus | AA1: MonthNames | AB1: ChecklistSections
A2: Bride | B2: Low | C2: Yes | D2: Yes | E2: Bride | F2: Family | G2: Chicken | H2: Venue | I2: Not Started | J2: Maid of Honor | K2: Need to Buy | L2: Ceremony | M2: Confirmed | N2: Buy | O2: Not Started | P2: Attire | Q2: Grand Hotel | R2: Before the Wedding | S2: Not Started | T2: Not Needed | U2: Not Due | V2: Deposit | W2: =TRUE() -> TRUE | X2: Party | Y2: USD | Z2: Researching | AA2: January | AB2: 12+ Months Before
A3: Groom | B3: Medium | C3: No | D3: No | E3: Groom | F3: Friend | G3: Beef | H3: Catering | I3: Ordered | J3: Bridesmaid | K3: Purchased | L3: Cocktail Hour | M3: To Be Decided | N3: Rent | O3: Ordered | P3: Hair | Q3: Riverside Inn | R3: Wedding Day | S3: In Progress | T3: Not Ordered | U3: Due Soon | V3: Progress Payment | W3: =FALSE() -> FALSE | X3: Trip | Y3: EUR | Z3: Contacted | AA3: February | AB3: 10-12 Months Before
A4: Both | B4: High | D4: Awaited | E4: Both | F4: Colleague | G4: Fish | H4: Photography | I4: Received | J4: Best Man | L4: Reception Entrance | M4: Cancelled | O4: Confirmed | P4: Makeup | Q4: Airport Marriott | R4: After the Wedding | S4: Completed | T4: Ordered | U4: Paid | V4: Final Payment | Y4: GBP | Z4: Booked | AA4: March | AB4: 8-10 Months Before
A5: Wedding Planner | B5: Urgent | F5: Neighbor | G5: Vegetarian | H5: Videography | I5: Fitting Scheduled | J5: Groomsman | L5: Reception Tables | O5: Delivered | P5: Shoes & Accessories | Q5: Boutique B and B | T5: Printed | U5: Overdue | V5: Gratuity | Y5: CAD | Z5: Paid | AA5: April | AB5: 6-8 Months Before
A6: Maid of Honor | F6: Other | G6: Vegan | H6: Florist | I6: Alterations Needed | J6: Flower Girl | L6: Head Table | P6: Nails | Q6: Guest House | Y6: AUD | Z6: Cancelled | AA6: May | AB6: 4-6 Months Before
A7: Best Man | G7: Kids Meal | H7: DJ/Band | I7: Ready | J7: Ring Bearer | L7: Cake Table | Y7: MXN | AA7: June | AB7: 2-4 Months Before
A8: Parent | G8: No Preference | H8: Officiant | J8: Usher | L8: Photo Booth | Y8: JPY | AA8: July | AB8: 1 Month Before
A9: Other | H9: Rentals | J9: Officiant | L9: Restrooms | AA9: August | AB9: 2 Weeks Before
H10: Decor | J10: Parent of Bride | L10: Other | AA10: September | AB10: 1 Week Before
H11: Hair & Makeup | J11: Parent of Groom | AA11: October | AB11: 2 Days Before
H12: Transportation | J12: Other | AA12: November | AB12: 1 Day Before
H13: Cake | AA13: December | AB13: Legal Items
H14: Stationery
H15: Favors
H16: Lighting
